Workbook
Name ELEFUND_tipo: ESTADO_EF5[TIPO ELEMENTO FUNDAMENTAL]
Name ESTADOEF: ESTADO_EF[ESTADO DE ELEMENTO FUNDAMENTAL]
Name IndicadoresCodigo: PESOS!$BD$3:$BD$45
Name Tipo_Pesos: PESOS_TIPOS[TIPO PESOS]

Sheet INDICADORES CUALITATIVOS
A1: NOMBRE DE LA INSTITUCIÓN: | D1: INSTITUTO SUPERIOR TECNOLÓGICO DE TÉCNICAS EMPRESARIALES Y DEL CONOCIMIENTO
A2: UBICACIÓN: | D2: Calle Isla Seymour N44-91 y Av. Río Coca
A3: TÉCNICO RESPONSABLE DEL PROCESO DE AUTOEVALUACIÓN: | D3: Héctor Alejandro López Paredes
A4: TÉCNICO RESPONSABLE DEL INDICADOR: | D4: Héctor Alejandro López Paredes
A5: CRITERIO ORGANIZACIÓN | R5: Tipo | S5: Columna en Matriz Pesos
A6: SUBCRITERIO PLANIFICACIÓN Y DESARROLLO
A7: Indicador: Planificación Estratégica Operativa | P7: TIPO DE PESOS | Q7: A. Pesos Con TP y MT | R7: {=+_xlfn.XLOOKUP(Q7,PESOS_TIPOS[[#All],[TIPO PESOS]],PESOS_TIPOS[[#All],[ORDEN PESOS]],"",0)} -> 1 | S7: {=+_xlfn.XLOOKUP(Q7,PESOS_TIPOS[[#All],[TIPO PESOS]],PESOS_TIPOS[[#All],[Columna]],"",0)} -> 8
A8: Nro. | B8: Elementos Fundamentales | C8: Clasificación de Elementos | D8: Valoración | E8: Nombres de las Evidencias | F8: Argumentación
A9: 1 | B9: Existe una normativa interna, aprobada y vigente, enmarcada en las normas nacionales, sobre el sistema de planificación que establece, al menos, los procedimientos para la elaboración, seguimiento, control y evaluación de la planificación, y la participación en ella de los diferentes actores. En caso de que la institución se gestione por procesos, el manual elaborado para normarlos, si cumple con las exigencias de este tipo de documento e incluye el ámbito de este indicador, equivale a la normativa que aquí se solicita. | C9: COMPLEMENTARIO | D9: NO CUMPLE | E9: No se carga evidencia que responda a este elemento fundamental | F9: No se cuenta con la normativa interna formal (reglamento, estatuto o manual de procedimientos aprobado por la instancia superior) que cumpla con los siguientes requisitos del elemento fundamental: Establecer los Procedimientos: No se evidencia el documento que defina formalmente los pasos, la metodología y los requisitos para la elaboración y actualización de la planificación. Normar el Control y Evaluación: No se presenta la normativa que establezca la periodicidad fija y los métodos específicos para el seguimiento, control y evaluación del PEDI y el POA. Definir la Participación: No se norma el mecanismo formal y obligatorio para la participación de los diferentes actores en el proceso de planificación institucional. En resumen, aunque el INTEC tiene planificación, carece de la evidencia de la norma legal interna que rige ese sistema de planificación, control y evaluación, lo cual es la exigencia central de este elemento fundamental. | Q9: 1.1.1 PEO | R9: ESENCIAL | S9: COMPLEMENTARIO
A10: 2 | B10: La planificación estratégica ha sido construida con el aporte de actores relevantes del entorno y la participación de representantes de las dependencias institucionales, y de otros actores institucionales relevantes. | C10: COMPLEMENTARIO | D10: CUMPLE | E10: Plan Estratégico de Desarrollo Institucional (PEDI) 2023-2028: Documento central de estrategia. | F10: En primer lugar, la planificación incorpora el aporte de actores relevantes del entorno. El PEDI incluye el Análisis Situacional (página 7), que abarca el contexto económico y los cambios en el país, y se complementa con un análisis de la Macro Legal (página 8). Esto indica que la institución consideró factores externos como el contexto productivo, la empleabilidad y la demanda para definir su estrategia. En segundo lugar, se evidencia la participación de actores institucionales relevantes. El diagnóstico del PEDI menciona que su diseño se basó en estudios de actores involucrados y análisis de percepción. Específicamente, se presenta el análisis de Autoevaluación Institucional (página 8), el cual es el resultado directo de la participación interna. Este proceso asegura que la estrategia institucional sea un reflejo de las perspectivas y necesidades de las diferentes dependencias y estamentos que conforman la comunidad del INTEC. | Q10: CANTIDAD DE EF | R10: =+COUNTIF(C9:C20,R9) -> 6 | S10: =+COUNTIF(C9:C20,S9) -> 6
A11: 3 | B11: La planificación estratégica es pertinente con la realidad del entorno institucional y, especialmente, con sus necesidades de transformación, en cuya satisfacción puede actuar la institución. Lo anterior debe reflejarse, apropiadamente, en el diagnóstico contenido en el PEDI. | C11: ESENCIAL | D11: CUMPLE | E11: Plan Estratégico de Desarrollo Institucional (PEDI) 2023-2028: Documento central de estrategia. | F11: La evidencia contenida en el PEDI 2023-2028 demuestra la pertinencia de la planificación al estar sustentada en un diagnóstico que refleja la realidad del entorno y las necesidades de transformación: En primer lugar, la pertinencia con la realidad del entorno se evidencia en el Análisis Situacional (página 7), el cual aborda el contexto económico del país, los estudios de empleabilidad y las tendencias del mercado. Esto garantiza que el PEDI no es un documento genérico, sino que está diseñado para responder a las demandas del ecosistema productivo. En segundo lugar, la planificación refleja las necesidades de transformación y la capacidad de la institución para actuar sobre ellas. El diagnóstico incluye el análisis de Autoevaluación Institucional (página 8), el cual identifica las fortalezas y debilidades internas. La conexión entre el diagnóstico de debilidades y los Objetivos Estratégicos asegura que la estrategia se enfoque en transformar áreas deficientes para la mejora continua. Por ejemplo, los objetivos suelen apuntar a mejorar la gestión de la investigación, la vinculación y la eficiencia interna, que son precisamente áreas de transformación necesarias en cualquier instituto. Por lo tanto, la planificación estratégica CUMPLE con la exigencia sustantiva de pertinencia, ya que su diagnóstico vincula la realidad externa (entorno y empleabilidad) con la necesidad de transformación interna de la institución. | Q11: VACIO | R11: =+COUNTIFS(C9:C20,R9,D9:D20,"") -> 0 | S11: =+COUNTIFS(C9:C20,S9,D9:D20,"") -> 0
A12: 4 | B12: La visión y los objetivos estratégicos del PEDI conforman una propuesta relevante de desarrollo académico de la institución en el más amplio sentido, cuyo logro reclama de la acción coherente, inteligente y esforzada de autoridades, profesores, trabajadores y estudiantes. | C12: ESENCIAL | D12: CUMPLE | E12: Plan Estratégico de Desarrollo Institucional (PEDI) 2023-2028: Documento central de estrategia. No cuenta con firmas de responsabilidad ni fecha de aprobación visible. Plan Operativo Anual (POA) 2025: Instrumento de desagregación de la estrategia. No cuenta con firmas de responsabilidad ni fecha de emisión visible. | F12: El PEDI cumple con el elemento fundamental que requiere que la visión y los objetivos estratégicos conformen una propuesta relevante de desarrollo académico en el sentido más amplio, cuyo logro exija la acción coherente de todos los actores. La Visión del INTEC (página 2 del POA y página 53 del PEDI) de "Ser reconocidos como la institución de educación superior que aporta positivamente a la sociedad desde la investigación" establece una meta relevante y ambiciosa que supera la simple función docente, abarcando explícitamente la investigación y el impacto social, y es respaldada por una Misión que declara la oferta académica a través de las cuatro funciones sustantivas: docencia, gestión, investigación y vinculación. Esta propuesta de desarrollo integral se concreta en los Objetivos Estratégicos del PEDI, los cuales se alinean con las funciones sustantivas y las necesidades de transformación identificadas en el diagnóstico. El logro de estos objetivos requiere la acción coordinada, que se materializa en el POA 2025, instrumento que desagrega las metas estratégicas en acciones específicas con asignación de recursos, plazos y responsables. Esta articulación operativa asegura que el esfuerzo planificado involucre y coordine de manera coherente las acciones de autoridades, profesores, trabajadores y, por extensión a través de programas de vinculación, de los estudiantes. Por lo tanto, el contenido del PEDI y la desagregación en el POA demuestran el cumplimiento sustantivo de este elemento fundamental. | Q12: CUMPLE | R12: =+COUNTIFS(C9:C20,R9,D9:D20,Q12) -> 5 | S12: =+COUNTIFS(C9:C20,S9,D9:D20,Q12) -> 3
A13: 5 | B13: El PEDI es coherente internamente, y se expresa; por ejemplo, en la correspondencia de la misión y visión institucionales con las conclusiones del diagnóstico interno y externo o, también, que el logro de los objetivos estratégicos planificados garantice alcanzar la visión, y así sucesivamente. | C13: ESENCIAL | D13: CUMPLE | E13: Plan Estratégico de Desarrollo Institucional (PEDI) 2023-2028: Documento central de estrategia. | F13: El PEDI cumple con el elemento fundamental ya que se demuestra al establecer una secuencia lógica y vinculante entre los componentes del plan. Por un lado, la Misión oferta las carreras a través de las cuatro funciones sustantivas y la Visión se enfoca a ser reconocidos por el aporte a la sociedad desde la investigación; ambas están directamente alineadas con los hallazgos del diagnóstico, el cual identifica tanto las fortalezas a mantener como las debilidades y oportunidades de mejora del entorno. Esta relación garantiza que los Objetivos Estratégicos no son metas aisladas, sino que se enfocan en superar las carencias internas y aprovechar las oportunidades externas detectadas. A su vez, el cumplimiento de estos objetivos, al fortalecer la investigación, la vinculación y la gestión interna, está diseñado para garantizar directamente la consecución de la Visión institucional. Por consiguiente, la estructura del PEDI evidencia la correspondencia exigida entre el diagnóstico, los fines institucionales y las metas planteadas. | Q13: NO CUMPLE | R13: =+COUNTIFS(C9:C20,R9,D9:D20,Q13) -> 1 | S13: =+COUNTIFS(C9:C20,S9,D9:D20,Q13) -> 3
A14: 6 | B14: El PEDI orienta con claridad el desarrollo estratégico de las funciones sustantivas a través de la misión, visión y objetivos estratégicos. En el PEDI deben quedar establecidos los niveles de progreso anuales que se deben alcanzar en el cumplimiento de los objetivos estratégicos. | C14: ESENCIAL | D14: CUMPLE | E14: Plan Estratégico de Desarrollo Institucional (PEDI) 2023-2028: Documento central de estrategia. | F14: El PEDI cumple sustantivamente con la exigencia de orientar el desarrollo estratégico de las funciones. La Misión del INTEC declara expresamente el desarrollo de las cuatro funciones sustantivas que son docencia, gestión, investigación y vinculación, y la Visión orienta el desarrollo institucional a ser reconocido por el aporte a la sociedad desde la investigación. Los Objetivos Estratégicos del PEDI están estructurados de forma congruente para abordar cada una de estas áreas, asegurando que la estrategia institucional sea integral y no se limite a la docencia. Respecto al requisito de establecer los niveles de progreso anuales, si bien el PEDI mismo establece los objetivos a largo plazo, el POA 2025 es el instrumento que cumple con esta función. El POA desagrega los Objetivos Estratégicos en Objetivos de Corto Plazo (OC) y Actividades concretas, asignando a cada una un indicador de cumplimiento, un plazo definido (con fechas específicas) y un presupuesto asociado. Esta desagregación temporal y cuantitativa demuestra el mecanismo mediante el cual el INTEC ha establecido los niveles de progreso anuales requeridos para la ejecución y seguimiento de su estrategia a largo plazo. | Q14: =+A7 -> Indicador: Planificación Estratégica Operativa | R14: {=_xlfn.IFS(AND(R12=R10,S12=S10),'DATOS BÁSICOS'!$A$15,AND(R12=R10,S12>0,S12<S10),'DATOS BÁSICOS'!$A$16,AND(R12>=1,S12<=S10),'DATOS BÁSICOS'!$A$17,R12=0,'DATOS BÁSICOS'!$A$18)} -> POCO-SATISFACTORIO
A15: 7 | B15: El POA debe construirse de manera articulada con el PEDI, a efectos de que su cumplimiento garantice que se alcancen los niveles de progreso previstos en el logro de los objetivos del PEDI para ese año. | C15: ESENCIAL | D15: CUMPLE | E15: Plan Estratégico de Desarrollo Institucional (PEDI) 2023-2028: Documento central de estrategia. No cuenta con firmas de responsabilidad ni fecha de aprobación visible. Plan Operativo Anual (POA) 2025. | F15: La articulación entre ambos documentos se evidencia en la estructura metodológica del POA: cada acción operativa está vinculada jerárquicamente a la estrategia. El POA no contiene actividades sueltas, sino que desagrega los Objetivos Estratégicos (OE) y los Objetivos de Corto Plazo (OC) del PEDI en tareas específicas. Esta vinculación asegura que el cumplimiento de las actividades detalladas en el POA, como por ejemplo: la gestión de admisiones o la promoción de tutorías, está directamente orientado a alcanzar el progreso anual requerido por los objetivos estratégicos establecidos a largo plazo en el PEDI. Al especificar para cada actividad un plazo, un indicador de cumplimiento y un presupuesto presente en el POA, el documento operacional se convierte en el mecanismo que garantiza que se alcancen los niveles de progreso previstos para el año 2025 dentro del marco estratégico 2023-2028.
A16: 8 | B16: El POA es la guía operativa del trabajo cotidiano de la institución y su cumplimiento se controla con la periodicidad establecida en la normativa citada, a efectos de tomar acciones correctivas. | C16: ESENCIAL | D16: NO CUMPLE | E16: Plan Operativo Anual (POA) 2025: Instrumento de desagregación de la estrategia. No cuenta con firmas de responsabilidad ni fecha de emisión visible. | F16: El POA cumple con ser la guía operativa del trabajo cotidiano de la institución, ya que detalla actividades específicas, como "Incorporar un CRM para mejorar la gestión del equipo de admisiones" o "Promover espacios de tutorías a estudiantes", las cuales corresponden directamente a las tareas diarias y los proyectos a corto plazo de las diferentes unidades. Al asignar fechas de inicio y fin, responsables específicos y recursos a cada una, el POA transforma la estrategia institucional en una lista de tareas concretas a ser ejecutadas y gestionadas diariamente. Sin embargo, el cumplimiento de la segunda parte del elemento fundamental que indica que el control se realice "con la periodicidad establecida en la normativa citada" y a efectos de tomar acciones correctivas, no se puede corroborar, debido a que no se cuenta con la normativa formal que establezca los plazos fijos (mensuales, trimestrales, etc.) y los procedimientos para el control y la toma de acciones correctivas, no es posible asegurar que el cumplimiento del POA se controle de manera sistemática y formal como lo requiere el modelo de evaluación. Por lo tanto, el POA CUMPLE en su función de ser la guía operativa, pero NO CUMPLE en demostrar que su control y evaluación están regidos por una normativa formal y que se garantice la periodicidad y las acciones correctivas exigidas.
A17: 9 | B17: El PEDI y/o el POA se actualizan cuando lo aconsejan las modificaciones ocurridas en las condiciones para su ejecución, se detectan claros errores en su elaboración o, como se indica al final de la Descripción, dar respuesta a nuevas exigencias en el ámbito de la calidad del desempeño institucional. Las modificaciones deben ser sustentadas, autorizadas y registradas, siguiendo el procedimiento establecido en la normativa interna sobre el sistema de planificación. | C17: COMPLEMENTARIO | D17: NO CUMPLE | E17: No se carga evidencia que responda a este elemento fundamental | F17: No se cuenta con un mecanismo formal y operativo para sustentar la necesidad de modificar el PEDI o el POA ante errores o nuevas exigencias de calidad; autorizar dichos cambios por la instancia competente; y registrar formalmente las modificaciones.
A18: 10 | B18: El representante institucional encargado puede explicar cómo está normado que funcione el sistema de planificación, cómo está funcionando, nivel de cumplimiento que se logra de las actividades del POA, dificultades en la aplicación del sistema y acciones correctivas al respecto. | C18: COMPLEMENTARIO | D18: CUMPLE | E18: Entrevista | F18: Durante la visita in situ se puede evidenciar el cumplimiento del indicador y el conocimiento del responsable.
A19: 11 | B19: Los representantes de cada área o dependencia institucional pueden explicar, sobre su área, el contenido de la planificación, sus fundamentos, cómo se está procediendo, el estado de su cumplimento, dificultades y deficiencias y acciones correctivas adoptadas. | C19: COMPLEMENTARIO | D19: CUMPLE | E19: Entrevista | F19: Durante la visita in situ se puede evidenciar el cumplimiento del indicador y el conocimiento del responsable.
A20: 12 | B20: En la web institucional está el PEDI y los POA que le corresponden hasta la fecha. Los integrantes de la comunidad educativa conocen la misión y visión institucionales, que se divulgan apropiadamente, y cuáles son las actividades del POA con las que ellos se relacionan por su rol en la institución y cómo marcha su cumplimiento. | C20: COMPLEMENTARIO | D20: NO CUMPLE | E20: No se carga evidencia que responda a este elemento fundamental | F20: No se cuenta con evidencia de la publicación de los documentos en la web institucional para garantizar la accesibilidad pública; los mecanismos de divulgación formal (manuales, resoluciones de socialización, etc.) que aseguren que la Misión y la Visión son apropiadamente conocidas por la comunidad; y los informes de seguimiento o cumplimiento del POA que demuestren que los integrantes conocen cómo marcha su cumplimiento.
A21: Valoración del Indicador: | C21: {=+IFERROR(IF((R11+S11)>0,"INGRESAR VALORACIÓN",_xlfn.IFS(AND(R12=R10,S12=S10),'DATOS BÁSICOS'!$A$15,AND(R12=R10,S12<>0,S12<S10),'DATOS BÁSICOS'!$A$16,AND(R12>=1,S12<=S10),'DATOS BÁSICOS'!$A$17,R12=0,'DATOS BÁSICOS'!$A$18)),"RESULTADO NO DEFINIDO")} -> POCO-SATISFACTORIO | D21: PESO DEL INDICADOR | E21: UTILIDAD
C22: =+IFERROR(VLOOKUP(C21,VALORACIÓN_INDI[],4,0),"") -> 0.35 | D22: =+VLOOKUP(Q9,PESOS!$BD$2:$BM$45,'INDICADORES CUALITATIVOS'!$S$7,0) -> 0.04 | E22: =+IFERROR(C22*D22,"") -> 0.014
A23: Observación General del Indicador
A26: Indicador: Relaciones Internacionales para el Desarrollo
A27: Nro. | B27: Elementos Fundamentales | C27: Clasificación de Elementos | D27: Valoración | E27: Nombre de la Evidencia | F27: Argumentación
A28: 1 | B28: El instituto planifica y ejecuta sus relaciones interinstitucionales, sobre la base de aprovechar las potencialidades de estas para elevar la calidad del desempeño institucional, especialmente en el desarrollo de las funciones sustantivas. Están dirigidas, preferentemente, a resolver las limitantes institucionales relacionadas con la introducción de innovaciones, la capacitación, el acceso a infraestructura técnica y equipamiento especializado y el desarrollo de proyectos académicos conjuntos. La planificación específica de cada acción incluye, al menos, los objetivos, procedimientos, participantes y cronograma de ejecución. La planificación de las acciones es coherente con los componentes de la planificación institucional (PEDI y POA) que se refieren a las relaciones interinstitucionales. | C28: ESENCIAL | D28: NO CUMPLE | E28: Ocho Acuerdos Marco y un Convenio Específico de Prácticas Pre Profesionales. | F28: No se cuenta con un documento que establezca la planificación específica de las relaciones interinstitucionales que contenga al menos: objetivos, procedimientos, participantes y cronograma de ejecución,para demostrar la gestión de proyectos, innovación, o capacitación especializada, debidamente aprobado y vigente. Los Acuerdos Marco por sí mismos solo establecen la intención, no la planificación de las acciones concretas. | Q28: 1.1.2 RID | R28: ESENCIAL | S28: COMPLEMENTARIO
A29: 2 | B29: Existe una normativa interna, aprobada y vigente, sobre relaciones interinstitucionales que establece, al menos, los objetivos, procedimientos, actores y dependencia institucional a cargo. En caso de que la institución se gestione por procesos, el manual elaborado para normarlos, si cumple con las exigencias de este tipo de documentos e incluye el ámbito de este indicador, equivale a la normativa que aquí se solicita. | C29: COMPLEMENTARIO | D29: NO CUMPLE | E29: No se carga evidencia que responda a este elemento fundamental | F29: No se cuenta con la Normativa Interna (Reglamento o Manual de Procedimientos) sobre la gestión de las relaciones interinstitucionales, debidamente aprobada y vigente, que defina claramente objetivos, procedimientos, actores y dependencia institucional a cargo. | Q29: CANTIDAD DE EF | R29: =+COUNTIF(C28:C35,R28) -> 4 | S29: =+COUNTIF(C28:C35,S28) -> 4
A30: 3 | B30: Los objetivos y los procedimientos de las acciones planificadas son coherentes con las necesidades institucionales que dieron origen a la acción, adecuadamente sustentadas en el diagnóstico institucional, con la capacidad de absorción del instituto y, en el caso de relaciones bilaterales, con las capacidades de la institución contraparte, según lo explicado en la Descripción. | C30: ESENCIAL | D30: NO CUMPLE | E30: No se carga evidencia que responda a este elemento fundamental | F30: No se cuenta con el Sustento Documental (informe de análisis o diagnóstico) que justifique la coherencia y pertinencia de la elección de cada contraparte y de las acciones a realizar, con base en una necesidad institucional diagnosticada y la capacidad de absorción del Instituto. | Q30: VACIO | R30: =+COUNTIFS(C28:C35,R28,D28:D35,"") -> 0 | S30: =+COUNTIFS(C28:C35,S28,D28:D35,"") -> 0
A31: 4 | B31: Las relaciones interinstitucionales han sido formalizadas a través de diversos instrumentos, preferentemente convenios. | C31: ESENCIAL | D31: CUMPLE | E31: Ocho Acuerdos Marco y un Convenio Específico de Prácticas Pre Profesionales. | F31: Se presenta como evidencia 9 convenios (8 Acuerdos Marco y 1 Convenio Específico), de los cuales 7 su objetivo principal es "el fomento académico e intercambio de experiencias en los campos de la docencia, la investigación, la cooperación al desarrollo y la cultura en general, así como, para la realización de prácticas profesionales y desarrollo de proyectos de vinculación, proyectos académicos, desarrollo de carreras, dentro de aquellas áreas en las cuales ambas entidades tengan interés manifiesto, con el fin de aunar esfuerzos para potenciar la capacitación de ambas instituciones", y 2 con enfoque para prácticas preprofesionales, cumpliendo con la exigencia de formalización mediante diversos instrumentos. | Q31: CUMPLE | R31: =+COUNTIFS(C28:C35,R28,D28:D35,Q31) -> 1 | S31: =+COUNTIFS(C28:C35,S28,D28:D35,Q31) -> 0
A32: 5 | B32: El responsable de las relaciones interinstitucionales puede explicar las acciones que se están realizando, el sustento de ellas, procedimientos que se emplean, resultados que se obtienen y direcciones en las que corresponde avanzar. Los profesores/estudiantes participantes pueden explicar lo relativo a la acción en la que intervinieron o intervienen y, especialmente, argumentar sobre su efectividad. | C32: COMPLEMENTARIO | D32: NO CUMPLE | E32: No se carga evidencia que responda a este elemento fundamental | F32: El Instituto carece de informes de ejecución y resultados y de listas de participantes certificadas que permitan al responsable institucional y a los participantes sustentar la efectividad de las acciones, los procedimientos empleados y los resultados obtenidos. Adicionalmente, no se han realizado verificaciones in situ con la finalidad de asegurar que los representante de cada área conozca como está normado y como funciona el proceso de planificación dentro de la dependencia a su cargo. | Q32: NO CUMPLE | R32: =+COUNTIFS(C28:C35,R28,D28:D35,Q32) -> 3 | S32: =+COUNTIFS(C28:C35,S28,D28:D35,Q32) -> 4
A33: 6 | B33: Se han realizado acciones de movilidad de profesores y estudiantes a nivel nacional o internacional. Los resultados alcanzados son satisfactorios. En la valoración de este elemento fundamental deben tenerse en cuenta los valores calculados para los indicadores de sustento Porcentaje de profesores que ha participado en acciones de movilidad y Porcentaje de estudiantes que participó en acciones de movilidad, que aparecen en la Descripción. | C33: COMPLEMENTARIO | D33: NO CUMPLE | E33: No se carga evidencia que responda a este elemento fundamental | F33: No se cuenta con la Lista Certificada de profesores o estudiantes que hayan participado en acciones de movilidad (diferentes a las prácticas pre profesionales obligatorias), ni con los informes que demuestren los resultados satisfactorios de dichas actividades. | Q33: =+A26 -> Indicador: Relaciones Internacionales para el Desarrollo | R33: {=+IFERROR(IF((R30+S30)>0,"INGRESAR VALORACIÓN",_xlfn.IFS(AND(R31=R29,S31=S29),'DATOS BÁSICOS'!$A$15,AND(R31=R29,S31>0,S31<S29),'DATOS BÁSICOS'!$A$16,AND(R31=1,S31<S29),'DATOS BÁSICOS'!$A$17,R31=0,'DATOS BÁSICOS'!$A$18)),"RESULTADO NO DEFINIDO")} -> POCO-SATISFACTORIO
A34: 7 | B34: Se han formalizado relaciones de colaboración con instituciones extranjeras, existe una planificación y hay actividades ejecutadas con un cumplimiento satisfactorio de sus objetivos. | C34: COMPLEMENTARIO | D34: NO CUMPLE | E34: Acuerdo Marco UNIR | F34: Aunque existe la formalización de un Acuerdo Marco con institución extranjera (UNIR), no se ha cargado la planificación específica de actividades ni los informes de ejecución que demuestren el cumplimiento satisfactorio de los objetivos de acciones concretas realizadas con la institución extranjera.
A35: 8 | B35: Existe un cumplimiento satisfactorio de los objetivos planteados en cada una de las acciones de las relaciones interinstitucionales. Las relaciones interinstitucionales son un aporte significativo al desarrollo institucional. Para la evaluación de este elemento fundamental se tendrá en cuenta, como otra fuente de información, el valor calculado para los indicadores de sustento Número de instituciones externas con las que se relaciona el instituto, promedio, por carrera y Número de redes académicas y del entorno de producción o servicios en las que participa efectivamente el instituto, promedio, por carrera, que aparecen en la Descripción. | C35: ESENCIAL | D35: NO CUMPLE | E35: Ocho Acuerdos Marco y un Convenio Específico de Prácticas Pre Profesionales. | F35: Si bien se cuenta con convenios formalizados, no se cuenta con informes de gestión o de cierre (Evidencia 6) que demuestren el cumplimiento satisfactorio de los objetivos planteados en cada convenio específico, ni que se pueda cuantificar el aporte significativo al desarrollo institucional.
A36: Valoración del Indicador: | C36: {=+IFERROR(IF((R30+S30)>0,"INGRESAR VALORACIÓN",_xlfn.IFS(AND(R31=R29,S31=S29),'DATOS BÁSICOS'!$A$15,AND(R31=R29,S31<>0,S31<S29),'DATOS BÁSICOS'!$A$16,AND(R31>=1,S31<=S29),'DATOS BÁSICOS'!$A$17,R31=0,'DATOS BÁSICOS'!$A$18)),"RESULTADO NO DEFINIDO")} -> POCO-SATISFACTORIO | D36: PESO DEL INDICADOR | E36: UTILIDAD
C37: =+IFERROR(VLOOKUP(C36,VALORACIÓN_INDI[],4,0),"") -> 0.35 | D37: =+VLOOKUP(Q28,PESOS!$BD$2:$BM$45,'INDICADORES CUALITATIVOS'!$S$7,0) -> 0.02 | E37: =+IFERROR(C37*D37,"") -> 0.007
A38: Observación General del Indicador
A42: Indicador: Aseguramiento Interno de la Calidad
A43: Nro. | B43: Elementos Fundamentales | C43: Clasificación de Elementos | D43: Valoración | E43: Nombre de la Evidencia | F43: Argumentación
A44: 1 | B44: La institución desarrolla acciones sistematizadas dirigidas al aseguramiento interno de la calidad (AIC), que se rigen por una normativa interna, aprobada y vigente, que se enmarca en las normas nacionales, especialmente, en los preceptos legales indicados en la Descripción. En la normativa del AIC se establecen, al menos, sus objetivos, estructura, actores, procedimientos de trabajo, incluidos los procedimientos para el desarrollo de la autoevaluación en todas sus fases y la dependencia institucional a cargo del AIC. En caso de que la institución se gestione por procesos, el manual elaborado para normarlos, si cumple con las exigencias de este tipo de documentos e incluye el ámbito de este indicador, equivale a la normativa que aquí se solicita. | C44: COMPLEMENTARIO | D44: NO CUMPLE | E44: No se carga evidencia que responda a este elemento fundamental | F44: No se cuenta con un normativa de aseguramiento de la calidad aprobada y vigente dentro del periodo de autoevaluación, que contenga al menos: objetivos, estructura, actores, procedimientos de trabajo, incluidos los procedimientos para el desarrollo de la autoevaluación en todas sus fases y la dependencia institucional a cargo del Aseguramiento Interno de la Calidad. | Q44: 1.1.3 AIC | R44: ESENCIAL | S44: COMPLEMENTARIO
A45: 2 | B45: Se divulga entre los actores institucionales la existencia, objetivos, procedimientos y actores del AIC. Se promociona la necesidad de la construcción colectiva de la calidad. | C45: COMPLEMENTARIO | D45: NO CUMPLE | E45: No se carga evidencia que responda a este elemento fundamental | F45: No se ha realizado acciones de divulgación de la existencia, objetivos, procedimientos y actores del Aseguramiento Interno de la Calidad (AIC). Por lo cua, no se cuenta con evidencias documentales (fotos, capturas web, material informativo) que demuestren la labor de divulgación sobre el AIC a la comunidad educativa dentro del período evaluado. | Q45: CANTIDAD DE EF | R45: =+COUNTIF(C44:C49,R44) -> 3 | S45: =+COUNTIF(C44:C49,S44) -> 3
A46: 3 | B46: Los procesos de autoevaluación se basan en estándares rigurosos y son planificados y ejecutados adecuadamente. Un proceso de autoevaluación puede abarcar el conjunto del desempeño institucional o convocarse diferentes procesos, según ámbitos específicos, en varios momentos. La autoevaluación se desarrolla según los lineamientos elegidos por la institución, que están indicados en la normativa. | C46: ESENCIAL | D46: NO CUMPLE | E46: Planificación y Actas del SAC: 4 actas de reuniones del comité de autoevaluación | F46: Se presenta evidencia de la Planificación del proceso de Autoevaluación y la conformación del comité mediante actas está fechada en el segundo semestre de 2025 (agosto y septiembre). Sin embargo, estas fechas son posteriores al límite de evaluación (primer semestre del 2025), por lo que no se puuede demuestrar la planificación y ejecución dentro del período. | Q46: VACIO | R46: =+COUNTIFS(C44:C49,R44,D44:D49,"") -> 0 | S46: =+COUNTIFS(C44:C49,S44,D44:D49,"") -> 0
A47: 4 | B47: Los resultados de la autoevaluación se divulgan entre la comunidad educativa de la institución y a partir de estos se generan acciones correctivas, de perfeccionamiento y estímulo que se incorporan, cuando corresponde, en la planificación estratégica/operativa. | C47: ESENCIAL | D47: NO CUMPLE | E47: No se carga evidencia que responda a este elemento fundamental | F47: Si bien el Plan Estratégico de Desarrollo Institucional (PEDI 2023 - 2028) demuestra que la planificación estratégica se basa en un proceso de Autoevaluación/Diagnóstico participativo (Análisis FODA), y las acciones correctivas y de perfeccionamiento generadas a partir de este diagnóstico están formalmente incorporadas en el POA INTEC 2025 mediante sus Objetivos y actividades, no se cuenta con un documento formal, informe o acta que demuestre la divulgación o comunicación explícita y periódica de los resultados finales de la Autoevaluación o Diagnóstico Institucional a la totalidad de la comunidad educativa. | Q47: CUMPLE | R47: =+COUNTIFS(C44:C49,R44,D44:D49,Q47) -> 0 | S47: =+COUNTIFS(C44:C49,S44,D44:D49,Q47) -> 1
A48: 5 | B48: Los actores del AIC demuestran dominio del modelo de evaluación institucional para institutos superiores del CACES, que debe ser un referente importante para establecer los estándares que guiarán los esfuerzos de mejoramiento de la calidad en la institución. | C48: COMPLEMENTARIO | D48: CUMPLE | E48: Certificados de Aprobación sobre el "Modelo de Evaluación Externa 2024" para el Rector (Jaime Ortega) y otros actores (Héctor López, Roberto Castro) con fecha de 28 de febrero de 2025. | F48: Los actores institucionales clave del AIC se han capacitado sobre el Modelo de Evaluación Externa del CACES, el cual se evidenicia en los certificados obtenidos en febrero de 2025. Los certificados de "Curso de Autoevaluación" de agosto de 2025 están fuera del período de autoevaluación. | Q48: NO CUMPLE | R48: =+COUNTIFS(C44:C49,R44,D44:D49,Q48) -> 3 | S48: =+COUNTIFS(C44:C49,S44,D44:D49,Q48) -> 2
A49: 6 | B49: Los actores del AIC acompañan a las diferentes dependencias institucionales en su labor para alcanzar los estándares de calidad que se ha planteado la institución, en correspondencia con el referente que ha adoptado. | C49: ESENCIAL | D49: NO CUMPLE | E49: No se carga evidencia que responda a este elemento fundamental | F49: No se carga evidencia documental (procedimientos de acompañamiento, relatorías o informes) que demuestre la ejecución de la función de acompañamiento y asistencia a las dependencias por parte de los actores del AIC. | Q49: =+A42 -> Indicador: Aseguramiento Interno de la Calidad | R49: {=_xlfn.IFS(AND(R47=R45,S47=S45),'DATOS BÁSICOS'!$A$15,AND(R47=R45,S47>0,S47<S45),'DATOS BÁSICOS'!$A$16,AND(R47>=1,S47<=S45),'DATOS BÁSICOS'!$A$17,R47=0,'DATOS BÁSICOS'!$A$18)} -> DEFICIENTE
A50: Valoración del Indicador: | C50: {=+IFERROR(IF((R46+S46)>0,"INGRESAR VALORACIÓN",_xlfn.IFS(AND(R47=R45,S47=S45),'DATOS BÁSICOS'!$A$15,AND(R47=R45,S47<>0,S47<S45),'DATOS BÁSICOS'!$A$16,AND(R47>=1,S47<=S45),'DATOS BÁSICOS'!$A$17,R47=0,'DATOS BÁSICOS'!$A$18)),"RESULTADO NO DEFINIDO")} -> DEFICIENTE | D50: PESO DEL INDICADOR | E50: UTILIDAD
C51: =+IFERROR(VLOOKUP(C50,VALORACIÓN_INDI[],4,0),"") -> 0 | D51: =+VLOOKUP(Q44,PESOS!$BD$2:$BM$45,'INDICADORES CUALITATIVOS'!$S$7,0) -> 0.03 | E51: =+IFERROR(C51*D51,"") -> 0
A52: Observación General del Indicador
A56: Indicador: Sistema informático de gestión
A57: Nro. | B57: Elementos Fundamentales | C57: Clasificación de Elementos | D57: Valoración | E57: Nombre de la Evidencia | F57: Argumentación
A58: 1 | B58: El SIG, incluida la herramienta de gestión documental, cuenta con un reglamento oficial, aprobado y vigente, que establece: su uso obligatorio para la gestión institucional, incluyendo la actualización de la información, objetivos, características generales, entidad responsable, deberes de los usuarios, normas para el funcionamiento y sanciones por incumplimiento del reglamento. | C58: COMPLEMENTARIO | D58: NO CUMPLE | E58: No se carga evidencia que responda a este elemento fundamental | F58: No se cuenta con un Reglamento del Sistema Informático de Gestión (SIG) debidamente aprobado y vigente, que contenda al menos los objetivos, la entidad responsable, los deberes de los usuarios, las normas de funcionamiento y el régimen sancionatorio que rige el uso del sistema. | Q58: 1.1.4 SIG | R58: ESENCIAL | S58: COMPLEMENTARIO
A59: 2 | B59: El SIG debe satisfacer las exigencias informativas del AIC, incluyendo los datos, evidencias documentales, valoraciones y cálculo de indicadores, relacionados con los procesos de autoevaluación. Debe contar con la flexibilidad requerida para adaptarse a especificidades institucionales y de carreras. | C59: ESENCIAL | D59: NO CUMPLE | E59: No se carga evidencia que responda a este elemento fundamental | F59: No se cuenta con documentación que permita constatar la existencia ni la operatividad de un módulo o funcionalidad específica dentro del SIG dedicado a la Autoevaluación Institucional (AIC) que permita la carga, valoración y el cálculo automatizado de los indicadores del Modelo de Evaluación a nivel institucional o de carrera, lo que impide demostrar la satisfacción de las exigencias informativas completas del AIC o su flexibilidad para adaptarse a las especificidades de las carreras. | Q59: CANTIDAD DE EF | R59: =+COUNTIF(C58:C65,R58) -> 5 | S59: =+COUNTIF(C58:C65,S58) -> 3
A60: 3 | B60: El SIG permite la realización de trámites académicos y administrativos de manera remota, desde computador de escritorio o desde dispositivos móviles, y reduce, en los trámites, el tiempo de respuesta, necesidad de desplazamientos, errores, tiempo para acceder a documentos, y prescindir, o en su defecto reducir, sustancialmente, las impresiones. | C60: ESENCIAL | D60: NO CUMPLE | E60: No se carga evidencia que responda a este elemento fundamental | F60: Se evidencia que el SIG permite la realización de trámites y gestiones de manera remota y digital, contribuyendo a la reducción de desplazamientos, errores e impresiones. La funcionalidad de trámites remotos está probada por el sistema centralizado de Tickets (soporte administrativo/técnico con trazabilidad y reportes) y por la gestión del Aula Virtual y Plataformas Estudiantiles (acceso a notas, materiales y simuladores). Específicamente, el Manual de Uso en Celular del Aula Virtual confirma la accesibilidad móvil para la interacción académica (descarga de archivos, rendición de cuestionarios), demostrando una reducción sustancial en la necesidad de impresiones. Sin embargo, a pesar que se cuenta con evidencia que es principalmente funcional-descriptiva (manuales) y no se cuenta con Reportes de Gestión de Trámites que verifiquen la reducción efectiva y cuantificable en el tiempo de respuesta de los trámites o la disminución de errores en los procesos administrativos y académicos más allá de las funcionalidades de trazabilidad del sistema de tickets. | Q60: VACIO | R60: =+COUNTIFS(C58:C65,R58,D58:D65,"") -> 0 | S60: =+COUNTIFS(C58:C65,S58,D58:D65,"") -> 0
A61: 4 | B61: El SIG auxilia la planificación, organización, control y evaluación de los procesos relacionados con las tres funciones sustantivas y los procesos administrativos, y disminuye los tiempos de ejecución y los errores, al realizar esas actividades. | C61: ESENCIAL | D61: NO CUMPLE | E61: Manual del uso del sistema académico para docentes Manual del uso del teams para docentes Manual del uso de las plataformas para estudiantes homologación Manual del uso de las plataformas para estudiantes regular Manual de gestión documental Manual de gestión de tickets | F61: Se evidencia que el Sistema Informático de Gestión (SIG), a través de sus componentes, permite la organización, control y evaluación de las funciones sustantivas y los procesos administrativos, lo que intrínsecamente contribuye a la disminución de tiempos y errores. Específicamente, el Sistema Académico y las Plataformas Estudiantiles prueban el apoyo directo a la función de Docencia (gestión de notas, materiales, evaluaciones), mientras que el Manual de Gestión Documental y el Manual de Tickets demuestran el apoyo a la organización y control administrativo mediante un repositorio estructurado (con carpetas para Investigación y Vinculación) y un sistema de trazabilidad de solicitudes. Sin embargo, la evidencia es principalmente descriptiva (manuales) y no incluye informes que cuantifiquen la disminución real de los tiempos de ejecución o errores en los procesos de Investigación y Vinculación con la Sociedad, lo que limitaría la constatación de la optimización efectiva. | Q61: CUMPLE | R61: =+COUNTIFS(C58:C65,R58,D58:D65,Q61) -> 0 | S61: =+COUNTIFS(C58:C65,S58,D58:D65,Q61) -> 1
A62: 5 | B62: Existe y está operativa, incorporada en el SIG o no, una herramienta de gestión documental que cumple con los estándares internacionales correspondientes y que opera un repositorio de los documentos de gestión de la actividad académica y administrativa. | C62: ESENCIAL | D62: NO CUMPLE | E62: Manual de Gestión Documental | F62: Se cuenta con el Manual de Gestión Documental, el cual describe el uso de Microsoft SharePoint como un repositorio estructurado y funcional para la gestión académica y administrativa. No obstante, no se cuenta con evidencia formal, certificación o declaración institucional que demuestre que la herramienta de gestión documental implementada cumple con los estándares internacionales correspondientes (como normas ISO de gestión documental o seguridad). | Q62: NO CUMPLE | R62: =+COUNTIFS(C58:C65,R58,D58:D65,Q62) -> 5 | S62: =+COUNTIFS(C58:C65,S58,D58:D65,Q62) -> 2
A63: 6 | B63: El SIG, incluida la herramienta de gestión documental, cuenta con un manual de usuario que contribuye a facilitar la interacción de estos con el sistema y que puede estar apoyado por tutoriales y otros recursos didácticos. | C63: COMPLEMENTARIO | D63: CUMPLE | E63: Manual de uso del sistema académico para docentes. Manual de gestión documental. Manual de uso del TEAMS para docentes. Manual uso plataformas estudiantes homologación. Manual uso plataformas estudiantes regulares Manual de gestión de tickets Manual del uso del aula virtual para docentes regular Manual del uso del aula virtual para docentes homologación Manual de uso en celular del aula virtual para estudiantes | F63: Se cuenta con manuales de usuario que, en conjunto, cumplen con el requisito de facilitar la interacción de la comunidad con el Sistema Informático de Gestión (SIG) y sus herramientas asociadas. Se presenta documentación para el Sistema Académico, el Sistema de Gestión Documental (SharePoint), la gestión de soporte (Tickets), y, de manera exhaustiva, para la Aula Virtual/LMS, cubriendo la operación para docentes (regular y homologación) y estudiantes. Adicionalmente, el "Manual de Uso en Celular del Aula Virtual para Estudiantes" funciona explícitamente como un recurso didáctico adicional y facilita la interacción móvil, satisfaciendo la totalidad de lo requerido. | Q63: =+A56 -> Indicador: Sistema informático de gestión | R63: {=+IFERROR(IF((R60+S60)>0,"INGRESAR VALORACIÓN",_xlfn.IFS(AND(R61=R59,S61=S59),'DATOS BÁSICOS'!$A$15,AND(R61=R59,S61>0,S61<S59),'DATOS BÁSICOS'!$A$16,AND(R61=1,S61<S59),'DATOS BÁSICOS'!$A$17,R61=0,'DATOS BÁSICOS'!$A$18)),"RESULTADO NO DEFINIDO")} -> DEFICIENTE
A64: 7 | B64: Los usuarios actuales, incluidos los nuevos profesores, estudiantes y empleados, han sido adecuadamente capacitados. Queda a opción de la institución la organización de cursos presenciales o de un MOOC, en cualquier caso, de aprobación obligatoria. Los usuarios muestran las habilidades requeridas al interactuar con el SIG, incluida la herramienta de gestión documental | C64: COMPLEMENTARIO | D64: NO CUMPLE | E64: No se carga evidencia que responda a este elemento fundamental | F64: No se cuenta con evidencia como programas de estudio, registros de asistencia con firmas, o certificados/notas de aprobación de cursos obligatorios/MOOC, que demuestren que los usuarios (docentes, estudiantes y empleados) han sido adecuadamente y obligatoriamente capacitados en el uso del SIG y sus componentes.
A65: 8 | B65: El SIG está totalmente operativo y da respuesta a las demandas de los usuarios sobre la base de contar con el equipamiento y el soporte técnico requeridos, propios o en contratación con externos. | C65: ESENCIAL | D65: NO CUMPLE | E65: Manual de gestión documental. Manual de gestión de tickets | F65: Se cuenta con la existencia de mecanismos de seguridad para el uso de las plataformas, principalmente a través de la descripción de la gestión de acceso y control, mismo que se establece en el Manual de Gestión Documental y el de Tickets, en el que se demuestran la implementación de control de accesos, roles y permisos mediante la plataforma SharePoint, asegurando la integridad de los datos por medio del historial de versiones y la trazabilidad de los cambios. Sin embargo, se cuenta con un Informe de Seguridad, una Política de Seguridad de la Información o un Plan de Copias de Seguridad formalmente documentado que demuestren su uso efectivo en áreas críticas como protocolos de contingencia o backups fuera del ecosistema del proveedor.
A66: Valoración del Indicador: | C66: {=+IFERROR(IF((R60+S60)>0,"INGRESAR VALORACIÓN",_xlfn.IFS(AND(R61=R59,S61=S59),'DATOS BÁSICOS'!$A$15,AND(R61=R59,S61<>0,S61<S59),'DATOS BÁSICOS'!$A$16,AND(R61>=1,S61<=S59),'DATOS BÁSICOS'!$A$17,R61=0,'DATOS BÁSICOS'!$A$18)),"RESULTADO NO DEFINIDO")} -> DEFICIENTE | D66: PESO DEL INDICADOR | E66: UTILIDAD
C67: =+IFERROR(VLOOKUP(C66,VALORACIÓN_INDI[],4,0),"") -> 0 | D67: =+VLOOKUP(Q58,PESOS!$BD$2:$BM$45,'INDICADORES CUALITATIVOS'!$S$7,0) -> 0.03 | E67: =+IFERROR(C67*D67,"") -> 0
A68: Observación General del Indicador
A71: SUBCRITERIO GESTIÓN SOCIAL
A72: Indicador: Igualdad de oportunidades
A73: Nro. | B73: Elementos Fundamentales | C73: Clasificación de Elementos | D73: Valoración | E73: Nombre de la Evidencia | F73: Argumentación
A74: 1 | B74: Existe una normativa interna aprobada y vigente de acción afirmativa, enmarcada en las normas nacionales, que contiene, al menos, los objetivos, políticas, procedimientos, beneficiarios, dependencia y otros actores. En caso de que la institución se gestione por procesos, el manual elaborado para normarlos, si cumple con las exigencias de este tipo de documentos e incluye el ámbito de este indicador, equivale a la normativa que aquí se solicita. | C74: COMPLEMENTARIO | D74: CUMPLE | E74: Plan de Igualdad 2023-2026 Reglamento de Becas y Ayudas Económicas | F74: Se cuenta con el Plan de Igualdad 2023-2026, aprobado por el Consejo Transitorio el 04 de diciembre de 2023, el cual establece objetivos y ejes estratégicos para la igualdad de oportunidades, no violencia ni discriminación. Adicionalmente, se cuenta con el Reglamento de Becas y Ayudas Económicas, el cual regula los procedimientos de otorgamiento de becas, una de las principales acciones afirmativas, y establece la Igualdad de oportunidades como principio general. Ambos documentos definen el marco normativo, objetivos y procedimientos para las acciones afirmativas. | Q74: 1.2.1 IDO | R74: ESENCIAL | S74: COMPLEMENTARIO
A75: 2 | B75: La normativa de acción afirmativa está en la web institucional y la comunidad educativa la conoce, especialmente lo referido a las posibilidades de beneficio que ofrece a las personas en condición de vulnerabilidad. | C75: COMPLEMENTARIO | D75: NO CUMPLE | E75: No se carga evidencia que responda a este elemento fundamental. | F75: No se cuenta con evidencias de la divulgación en la web institucional y del conocimiento por la comunidad educativa. Se requiere una captura de pantalla o URL que demuestre la publicación de la normativa de acción afirmativa o del Plan de Igualdad en la web institucional, así como los registros de entrevistas a miembros de la comunidad educativa que corroboren el conocimiento de la misma. | Q75: CANTIDAD DE EF | R75: =+COUNTIF(C74:C78,R74) -> 2 | S75: =+COUNTIF(C74:C78,S74) -> 3
A76: 3 | B76: La intensidad de las acciones afirmativas orientadas al conjunto de la comunidad educativa, están en correspondencia con sus necesidades y las del entorno. Para el análisis de este elemento fundamental se tendrán en cuenta las consideraciones y el resultado del cálculo del indicador cuantitativo de sustento “Estudiantes beneficiados por acciones afirmativas”, incluidos en la Descripción. | C76: ESENCIAL | D76: NO CUMPLE | E76: Reglamento de Becas y Ayudas Económicas Contratos de Beca Complementaria (Futuro Femenino) | F76: Se cuenta con el Reglamento de Becas y Ayudas Económicas y documentos de ejecución como el Contrato de Beca Complementaria, que demuestran la existencia y ejecución de acciones afirmativas (becas de rendimiento, ayuda económica, etc.). Sin embargo, no se cuenta con el resultado del cálculo del indicador cuantitativo de sustento (Estudiantes beneficiados por acciones afirmativas). Para justificar plenamente el cumplimiento, se requiere un Informe certificado que contenga el resultado del cálculo del indicador cuantitativo de sustento, que permita evaluar la intensidad de las acciones en relación con las necesidades. | Q76: VACIO | R76: =+COUNTIFS(C74:C78,R74,D74:D78,"") -> 0 | S76: =+COUNTIFS(C74:C78,S74,D74:D78,"") -> 0
A77: 4 | B77: La intensidad de las acciones afirmativas orientadas específicamente hacia las mujeres, están en correspondencia con las necesidades de las profesoras, estudiantes y trabajadoras. Para el análisis de este elemento fundamental se tendrán en cuenta las consideraciones y el resultado del cálculo de los indicadores cuantitativos de sustento incluidos en la Descripción. El análisis de los resultados de los indicadores cuantitativos de sustento se debe hacer sobre la base de tres comparaciones, cuyo orden de presentación no indica jerarquía ni la secuencia en que deben ser realizadas: i. Comparar el resultado del indicador b) Profesoras en cargos de dirección académica, con el resultado del indicador a) Profesoras en el instituto. ii. Comparar el resultado del indicador d) Profesoras en procesos de capacitación, con el resultado del indicador c) Profesores totales en procesos de capacitación. iii. Comparar el resultado del indicador f) Profesoras cuyo máximo título es un grado universitario y se encuentran cursando una maestría académica en una universidad o una maestría tecnológica, con el resultado del indicador e) Profesores totales cuyo máximo título es un grado universitario y se encuentran cursando una maestría académica en una universidad o una maestría tecnológica. | C77: ESENCIAL | D77: NO CUMPLE | E77: Plan de Igualdad 2023-2026 Contratos de Beca Complementaria (Futuro Femenino) | F77: Se cuenta con el Plan de Igualdad 2023-2026, que define un eje estratégico para la no violencia y no abuso hacia las mujeres; y Contratos de Beca Complementaria dentro del programa "FUTURO FEMENINO" (73 becas), lo que demuestra acciones afirmativas específicas para mujeres. Sin embargo, se requiere tres comparaciones de indicadores cuantitativos específicos sobre profesoras en cargos de dirección y capacitación. Para justificar plenamente el cumplimiento, se requiere la Lista certificada de profesores cuyo máximo título es un grado universitario y el Informe certificado con el resultado del cálculo de los indicadores cuantitativos de sustento, datos con los que no se cuenta. | Q77: CUMPLE | R77: =+COUNTIFS(C74:C78,R74,D74:D78,Q77) -> 0 | S77: =+COUNTIFS(C74:C78,S74,D74:D78,Q77) -> 1
A78: 5 | B78: El instituto desarrolla, por diferentes vías, una acción educativa sistemática dirigida a desarrollar una conciencia de igualdad plena entre todas las personas, para hacer desaparecer las percepciones discriminatorias de cualquier origen “etnia, lugar de nacimiento, edad, sexo, identidad de género, identidad cultural, estado civil, idioma, religión, ideología, filiación política, pasado judicial, condición socio-económica, condición migratoria, orientación sexual, estado de salud, portar VIH, discapacidad, diferencia física; ni por cualquier otra distinción, personal o colectiva, temporal o permanente, que tenga por objeto o resultado menoscabar o anular el reconocimiento, goce o ejercicio de los derechos.” (Constitución de la República, 2008, Art. 11, literal 2). | C78: COMPLEMENTARIO | D78: NO CUMPLE | E78: Plan de Igualdad 2023-2026 Informe sobre diagnóstico institucional Plan de Igualdad | F78: Se cuenta con el Plan de Igualdad 2023-2026 y el Informe sobre diagnóstico institucional Plan de Igualdad, que establecen las líneas de acción y el objetivo de sensibilizar a la comunidad educativa para evitar la discriminación y promover la igualdad. Sin embargo, no se cuenta con la evidencia de la ejecución sistemática de estas actividades, mismas que deben plasmarse en un planificación de las acciones educativas, informes de cumplimiento de esas actividades y el material explícito (publicidad impresa o digital). | Q78: NO CUMPLE | R78: =+COUNTIFS(C74:C78,R74,D74:D78,Q78) -> 2 | S78: =+COUNTIFS(C74:C78,S74,D74:D78,Q78) -> 2
A79: Valoración del Indicador: | C79: {=+IFERROR(IF((R76+S76)>0,"INGRESAR VALORACIÓN",_xlfn.IFS(AND(R77=R75,S77=S75),'DATOS BÁSICOS'!$A$15,AND(R77=R75,S77<>0,S77<S75),'DATOS BÁSICOS'!$A$16,AND(R77>=1,S77<=S75),'DATOS BÁSICOS'!$A$17,R77=0,'DATOS BÁSICOS'!$A$18)),"RESULTADO NO DEFINIDO")} -> DEFICIENTE | D79: PESO DEL INDICADOR | E79: UTILIDAD | Q79: =+A72 -> Indicador: Igualdad de oportunidades | R79: {=_xlfn.IFS(AND(R77=R75,S77=S75),'DATOS BÁSICOS'!$A$15,AND(R77=R75,S77>0,S77<S75),'DATOS BÁSICOS'!$A$16,AND(R77>=1,S77<=S75),'DATOS BÁSICOS'!$A$17,R77=0,'DATOS BÁSICOS'!$A$18)} -> DEFICIENTE
C80: =+IFERROR(VLOOKUP(C79,VALORACIÓN_INDI[],4,0),"") -> 0 | D80: =+VLOOKUP(Q74,PESOS!$BD$2:$BM$45,'INDICADORES CUALITATIVOS'!$S$7,0) -> 0.03 | E80: =+IFERROR(C80*D80,"") -> 0
A81: Observación General del Indicador
A84: Indicador: Ética y transparencia
A85: Nro. | B85: Elementos Fundamentales | C85: Clasificación de Elementos | D85: Valoración | E85: Nombre de la Evidencia | F85: Argumentación
A86: 1 | B86: El funcionamiento del instituto se basa en el respeto estricto a la constitución, a las leyes y a las normas de menor jerarquía que le atañen. Existe y se aplica, correctamente, un código de ética institucional que incluye normas generales en este ámbito, normas específicas que deben regir en una institución educativa, incluyendo las referidas a las relaciones entre profesores y estudiantes y el funcionamiento del comité de ética, así como las normas que, apoyadas en la utilización de los instrumentos técnicos apropiados, contribuyen a prevenir y corregir las prácticas académicas deshonestas. El código de ética del instituto ha sido elaborado en el marco de la normativa nacional pertinente. En aspectos particulares, la institución se rige también por los principios deontológicos que corresponden a las carreras que se cursan en la institución. | C86: ESENCIAL | D86: NO CUMPLE | E86: No se carga evidencia que responda a este elemento fundamental. | F86: No se cuenta con la evidencia Código de ética de la institución formalmente aprobada que consolide las normas generales, las reglas sobre las relaciones profesor-estudiante, las disposiciones para la prevención y corrección de la deshonestidad académica (fraude y plagio), y las normas que regulan la composición y funcionamiento del Comité de Ética. | Q86: 1.2.2 YET | R86: ESENCIAL | S86: COMPLEMENTARIO
A87: 2 | B87: Las normas incluidas en el código de ética institucional se divulgan y son conocidas por estudiantes y profesores, especialmente aquellas que atañen a las instituciones educativas en general y a la actividad académica en particular. | C87: ESENCIAL | D87: NO CUMPLE | E87: Informes de Gestión PEDI 2023-2028 | F87: No se cuenta con evidencia que demuestre la divulgación de las normas de ética o del código institucional. Se cuenta con los Informes de Gestión y el Plan Estratégico de Desarrollo Institucional (PEDI) hacen referencia a la conducta ética como parte de la misión y visión, sin embargo, no se han proporcionado documentos específicos como actas de capacitación o inducción a estudiantes y profesores sobre las normas éticas, ni capturas de pantalla de la página web institucional que evidencien la publicación de la normativa. | Q87: CANTIDAD DE EF | R87: =+COUNTIF(C86:C98,R86) -> 5 | S87: =+COUNTIF(C86:C98,S86) -> 8
A88: 3 | B88: En la institución existe y funciona un comité de ética que está integrado por representantes de la comunidad educativa que cuentan con un elevado reconocimiento por su honorabilidad. El comité tiene como misión conocer, reflexionar, alertar y educar en los temas relacionados con el comportamiento ético de los miembros de la comunidad educativa. | C88: COMPLEMENTARIO | D88: NO CUMPLE | E88: No se carga evidencia que responda a este elemento fundamental. | F88: No se cuenta con el Acta de Conformación del Comité de Ética, el Plan de Trabajo Anual y las Actas de Sesiones, donde se constate la creación y funcionamiento de este órgano, así como, para justificar el cumplimiento de actividades, conocimiento, reflexión, alerta y educación sobre temas de ética institucional. | Q88: VACIO | R88: =+COUNTIFS(C86:C98,R86,D86:D98,"") -> 0 | S88: =+COUNTIFS(C86:C98,S86,D86:D98,"") -> 0
A89: 4 | B89: La información que ofrece el instituto, por cualquier vía, a la comunidad educativa o a la sociedad en general, sobre sus fines, oferta académica, costos, funcionamiento, condiciones, resultados, autoridades, profesores, estudiantes y otros aspectos académicos o administrativos es verídica, actualizada y clara. | C89: COMPLEMENTARIO | D89: NO CUMPLE | E89: Informes de Rendición de Cuentas (2023 y 2024) Resolución No. 007-OCS-INTEC-2025 Informes de Encuesta de Satisfacción Estudiantil y Percepción Empresarial | F89: Se cuenta con los Informes de Rendición de Cuentas (2023 y 2024), la Resolución No. 007-OCS-INTEC-2025 que aprueba y ordena la remisión de dicho informe al CES, y los Informes de Encuesta de Satisfacción Estudiantil y Percepción Empresarial como insumos de transparencia; no obstante, no se cuenta con el documento específico (metodología, convocatoria o acta) que formalice la ejecución del mecanismo público de participación de la comunidad institucional y la sociedad, que es la documentación formal de la Audiencia Pública o el registro de la participación directa en el proceso de rendición. | Q89: CUMPLE | R89: =+COUNTIFS(C86:C98,R86,D86:D98,Q89) -> 2 | S89: =+COUNTIFS(C86:C98,S86,D86:D98,Q89) -> 2
A90: 5 | B90: Las autoridades rinden cuenta de su gestión, al menos, anualmente, ante la comunidad educativa. | C90: COMPLEMENTARIO | D90: CUMPLE | E90: Rendición de Cuentas A diciembre 2024 RESOLUCIÓN No.007-OCS-INTEC-2025 Rendición de Cuentas A diciembre 2023 RESOLUCIÓN No.012-CT-INTEC-2024 | F90: Se cuenta con los informes de Rendición de Cuentas a diciembre 2023 y a diciembre 2024.pdf, y las respectivas actas de aprobación representadas por resolución No.012-CT-INTEC-2024 y No.007-OCS-INTEC-2025, respectivamente, lo que prueba el cumplimiento anual de la obligación de rendición de cuentas. | Q90: NO CUMPLE | R90: =+COUNTIFS(C86:C98,R86,D86:D98,Q90) -> 3 | S90: =+COUNTIFS(C86:C98,S86,D86:D98,Q90) -> 6
A91: 6 | B91: La comunidad educativa expresa su confianza en que la institución se gestiona de modo ético y transparente, y que el mérito y esfuerzo académico, y el buen comportamiento social, son la base para valorar a los miembros de la comunidad educativa. | C91: ESENCIAL | D91: CUMPLE | E91: Entrevista | F91: El elemento será verificado durante la visita in situ | Q91: =+A84 -> Indicador: Ética y transparencia | R91: {=_xlfn.IFS(AND(R89=R87,S89=S87),'DATOS BÁSICOS'!$A$15,AND(R89=R87,S89>0,S89<S87),'DATOS BÁSICOS'!$A$16,AND(R89>=1,S89<=S87),'DATOS BÁSICOS'!$A$17,R89=0,'DATOS BÁSICOS'!$A$18)} -> POCO-SATISFACTORIO
A92: 7 | B92: La comunidad educativa considera verídica y suficiente la información que recibe de las autoridades institucionales | C92: ESENCIAL | D92: CUMPLE | E92: Entrevista | F92: El elemento será verificado durante la visita in situ
A93: 8 | B93: La comunidad educativa no teme retaliación por parte de las autoridades cuando se hacen reclamos o críticas. | C93: COMPLEMENTARIO | D93: CUMPLE | E93: Entrevista | F93: El elemento será verificado durante la visita in situ
A94: 9 | B94: Existe una imagen positiva de la institución en su entorno. No hay cuestionamientos públicos fundados sobre el funcionamiento ético y la transparencia de la institución. | C94: COMPLEMENTARIO | D94: NO CUMPLE | E94: No se carga evidencia que responda a este elemento fundamental. | F94: No se cuenta con captación de información sobre opiniones de la comunidad del entorno, noticias de la prensa local, etc., para recopilar información externa que valide la imagen pública y la ausencia de cuestionamientos fundados sobre la ética y transparencia de la institución.
A95: 10 | B95: El Órgano Colegiado Superior funciona según las normas aprobadas y en un ambiente de libertad de expresión. | C95: COMPLEMENTARIO | D95: NO CUMPLE | E95: No se carga evidencia que responda a este elemento fundamental. | F95: Se cuenta con documentos parciales de funcionamiento como RESOLUCIÓN No.012-CT-INTEC-2024 y RESOLUCIÓN No.007-OCS-INTEC-2025, pero no se cuenta con el juego completo de Actas de las sesiones ordinarias y extraordinarias del Órgano Colegiado Superior para verificar el cumplimiento integral de las normas, ni con las entrevistas a miembros de la comunidad educativa para confirmar el ambiente de libertad de expresión.
A96: 11 | B96: No hay sanciones administrativas ejecutoriadas contra la institución por cuestiones que tienen que ver con el comportamiento ético de esta en los ámbitos laboral, tributario y ambiental. | C96: COMPLEMENTARIO | D96: NO CUMPLE | E96: No se carga evidencia que responda a este elemento fundamental. | F96: No se cuenta con la Certificación del instituto en la que se haga constar que no se han recibido sanciones administrativas ejecutoriadas contra la institución por cuestiones que tienen que ver con el comportamiento ético de esta en los ámbitos indicados, documento que debe presentarse para probar formalmente la inexistencia de sanciones ejecutoriadas.
A97: 12 | B97: El instituto realiza las acciones educativas, preventivas y correctivas necesarias en relación con los actos de deshonestidad académica, especialmente, el fraude durante los exámenes, el plagio y la violación del código de ética en las investigaciones y el desarrollo experimental. | C97: ESENCIAL | D97: NO CUMPLE | E97: No se carga evidencia que responda a este elemento fundamental. | F97: No se cuenta con las Evidencias de las acciones preventivas y correctivas de la deshonestidad académica, que incluyen documentos como normas internas, código de ética de investigación, y actas de procesos disciplinarios. Adicionalmente, se requiere presentar las Evidencias de la divulgación del código de ética y de la labor educativa desarrollada al respecto para complementar la acción preventiva.
A98: 13 | B98: Los estados financieros de la institución entregados al CES, las remuneraciones de las autoridades, profesores, investigadores, servidores y trabajadores, el PEDI y el POA, los informes de rendición de cuentas y las normas internas de la institución en los diferentes ámbitos, deben estar en la web institucional. | C98: COMPLEMENTARIO | D98: NO CUMPLE | E98: No se carga evidencia que responda a este elemento fundamental. | F98: Se cuenta con los informes de Rendición de Cuentas, pero no se cuenta con un documento del link de la página web de la institución y capturas de pantalla del mismo para verificar la publicación y accesibilidad de todos los documentos e informes requeridos en el sitio web institucional.
A99: Valoración del Indicador: | C99: {=+IFERROR(IF((R88+S88)>0,"INGRESAR VALORACIÓN",_xlfn.IFS(AND(R89=R87,S89=S87),'DATOS BÁSICOS'!$A$15,AND(R89=R87,S89<>0,S89<S87),'DATOS BÁSICOS'!$A$16,AND(R89>=1,S89<=S87),'DATOS BÁSICOS'!$A$17,R89=0,'DATOS BÁSICOS'!$A$18)),"RESULTADO NO DEFINIDO")} -> POCO-SATISFACTORIO | D99: PESO DEL INDICADOR | E99: UTILIDAD
C100: =+IFERROR(VLOOKUP(C99,VALORACIÓN_INDI[],4,0),"") -> 0.35 | D100: =+VLOOKUP(Q86,PESOS!$BD$2:$BM$45,'INDICADORES CUALITATIVOS'!$S$7,0) -> 0.03 | E100: =+IFERROR(C100*D100,"") -> 0.0105
A101: Observación General del Indicador
A104: Indicador: Bienestar psicológico
A105: Nro. | B105: Elementos Fundamentales | C105: Clasificación de Elementos | D105: Valoración | E105: Nombre de la Evidencia | F105: Argumentación
A106: 1 | B106: La propuesta pedagógica de la institución reconoce la necesidad de trabajar por el bienestar psicológico de los integrantes de la comunidad educativa y establece los caminos para ello, como una contribución significativa al propósito de contar con una sociedad más feliz. | C106: COMPLEMENTARIO | D106: NO CUMPLE | E106: NO CUMPLE | F106: Plan de Igualdad 2023-2026 Informe sobre diagnóstico institucional Plan de Igualdad | G106: No se cuenta con los documentos con la propuesta pedagógica de la institución, que es el documento formal requerido para demostrar la incorporación explícita del bienestar psicológico en el modelo educativo troncal. Aunque el PLAN DE IGUALDAD 2023-2026 y el Informe sobre diagnóstico institucional Plan de Igualdad aluden a ejes estratégicos de bienestar, no sustituyen la Propuesta Pedagógica en sí misma. | Q106: 1.2.3 BPS | R106: ESENCIAL | S106: COMPLEMENTARIO
A107: 2 | B107: Los estudiantes tienen confianza en el éxito en sus estudios y aprecian que las autoridades institucionales y sus profesores son agentes positivos para identificar y desarrollar en ellos sus fortalezas y virtudes, su propósito de vida, la autoestima, la autodeterminación y la autoconfianza. Valoran como agradable, y estimulante para la realización de sus proyectos de vida, educarse en la institución. | C107: ESENCIAL | D107: NO CUMPLE | E107: NO CUMPLE | F107: Informe de Encuesta de Satisfacción Estudiantil VCC | G107: Se cuenta con el Informe de Encuesta de Satisfacción Estudiantil VCC, el cual proporciona evidencia cuantitativa sobre la apreciación general de los estudiantes. Sin embargo, no se cuenta con la captación de información sobre apreciaciones de los integrantes de la comunidad educativa, la cual debe presentarse para complementar la encuesta mediante entrevistas o grupos focales que validen la percepción sobre el desarrollo de fortalezas y el propósito de vida. (visita in situ) | Q107: CANTIDAD DE EF | R107: =+COUNTIF(C106:C110,R106) -> 3 | S107: =+COUNTIF(C106:C110,S106) -> 2
A108: 3 | B108: Los profesores y los trabajadores se sienten tratados de manera respetuosa y afable por las autoridades, que se preocupan por generar un ambiente de trabajo saludable que potencia el bienestar físico y psicológico, y reconocen que la institución es un espacio de crecimiento profesional y personal. Valoran como agradable, y estimulante para la realización de sus proyectos de vida, ser parte de la institución. | C108: ESENCIAL | D108: CUMPLE | E108: NO CUMPLE | F108: Informe de Encuesta de Satisfacción Docentes INTEC | G108: Se cuenta con el Informe de Encuesta de Satisfacción Docentes INTEC, que ofrece evidencia cuantitativa sobre la satisfacción del claustro. No obstante, no se cuenta con la captación de información sobre apreciaciones de los integrantes de la comunidad educativa, la cual debe presentarse para complementar la encuesta con entrevistas o grupos focales que confirmen el ambiente de trabajo saludable y el trato respetuoso por parte de las autoridades. (visita in situ) | Q108: VACIO | R108: =+COUNTIFS(C106:C110,R106,D106:D110,"") -> 0 | S108: =+COUNTIFS(C106:C110,S106,D106:D110,"") -> 0
A109: 4 | B109: El instituto ha diseñado y ejecuta, satisfactoriamente, a través de la unidad de bienestar estudiantil, proyectos de intervención basados en la psicología positiva, fundamentados científicamente, para potenciar el bienestar psicológico en la comunidad educativa. | C109: ESENCIAL | D109: CUMPLE | E109: NO CUMPLE | F109: Videos: Charla. Cuidando nuestra salud mental claves para el bienestar académico y personal; Grabación de la reunión de Invitación a Charla Cultura institucional basada en el respeto y la igualdad; Invitación a Charla Admisiones inclusivas y sin barreras; Invitación a Charla Admisiones inclusivas y sin barreras; Invitación a Charla Diversidad y acceso equitativo a la educación construyendo una comunidad inclusiva; Liderazgo con Equidad Formando Representantes que Inspiran; 2 videos de Reunión en General. | G109: Se cuenta con evidencias de la ejecución de los programas de intervención positiva a través de los videos anexos, como por ejemplo: la charla de "Cuidando nuestra salud mental claves para el bienestar académico y personal". Sin embargo, no se cuenta con un documento de los proyectos de intervención basados en la psicología positiva con los componentes y requisitos indicados en la descripción, que son necesarios para demostrar el diseño formal, la fundamentación científica y la planificación estructurada de estos programas. | Q109: CUMPLE | R109: =+COUNTIFS(C106:C110,R106,D106:D110,Q109) -> 2 | S109: =+COUNTIFS(C106:C110,S106,D106:D110,Q109) -> 1
A110: 5 | B110: Se evalúan los resultados obtenidos en estudiantes y profesores en los programas de intervención basados en la psicología positiva. | C110: COMPLEMENTARIO | D110: CUMPLE | E110: CUMPLE | F110: Informe de Encuesta de Satisfacción Docentes INTEC Informe de Encuesta de Satisfacción Estudiantil VCC | G110: No se cuenta con un Informe de evaluación de resultados de los programas de intervención basada en la psicología positiva, que es el documento que debe presentarse para demostrar la medición de la efectividad de las acciones realizadas. Los informes de encuestas de satisfacción anexados (Informe de Encuesta de Satisfacción Docentes INTEC e Informe de Encuesta de Satisfacción Estudiantil VCC) no son sustitutos directos de una evaluación de resultados específica del programa. | Q110: NO CUMPLE | R110: =+COUNTIFS(C106:C110,R106,D106:D110,Q110) -> 1 | S110: =+COUNTIFS(C106:C110,S106,D106:D110,Q110) -> 1
A111: Valoración del Indicador: | C111: {=+IFERROR(IF((R108+S108)>0,"INGRESAR VALORACIÓN",_xlfn.IFS(AND(R109=R107,S109=S107),'DATOS BÁSICOS'!$A$15,AND(R109=R107,S109<>0,S109<S107),'DATOS BÁSICOS'!$A$16,AND(R109>=1,S109<=S107),'DATOS BÁSICOS'!$A$17,R109=0,'DATOS BÁSICOS'!$A$18)),"RESULTADO NO DEFINIDO")} -> POCO-SATISFACTORIO | D111: PESO DEL INDICADOR | E111: UTILIDAD | Q111: =+A104 -> Indicador: Bienestar psicológico | R111: {=_xlfn.IFS(AND(R109=R107,S109=S107),'DATOS BÁSICOS'!$A$15,AND(R109=R107,S109>0,S109<S107),'DATOS BÁSICOS'!$A$16,AND(R109>=1,S109<=S107),'DATOS BÁSICOS'!$A$17,R109=0,'DATOS BÁSICOS'!$A$18)} -> POCO-SATISFACTORIO
C112: =+IFERROR(VLOOKUP(C111,VALORACIÓN_INDI[],4,0),"") -> 0.35 | D112: =+VLOOKUP(Q106,PESOS!$BD$2:$BM$45,'INDICADORES CUALITATIVOS'!$S$7,0) -> 0.03 | E112: =+IFERROR(C112*D112,"") -> 0.0105
A113: Observación General del Indicador
A116: CRITERIO INFRAESTRUCTURA
...

Sheet Sheet1
A2: Nombre | B2: Area | C2: Tecnologia
A3: fecha | B3: 46140
A4: tema de la reunion | B4: Revision del sistema SIG
A6: detalles
A11: Participantes | B11: firmas
A12: fabricio borja
A13: fernando osorio
A14: Hector lopez
A18: fecha de la proxima revision | B18: tentativa

Sheet DATOS BÁSICOS
A3: ESTADO DE ELEMENTO FUNDAMENTAL
A4: CUMPLE
A5: NO CUMPLE
A7: TIPO ELEMENTO FUNDAMENTAL
A8: COMPLEMENTARIO
A9: ESENCIAL
B13: CONDICION 1 | C13: CONDICIÓN 2
A14: VALORACIÓN | B14: ESCENCIAL | C14: COMPLEMENTARIO | D14: Valor
A15: SATISFACTORIO | B15: CUMPLE CON TODOS LOS ELEMENTOS | C15: CUMPLE CON TODOS LOS ELEMENTOS | D15: 1
A16: CUASI-SATISFACTORIO | B16: CUMPLE CON TODOS LOS ELEMENTOS | C16: NO CUMPLE CON TODOS LOS ELEMENTOS | D16: 0.7
A17: POCO-SATISFACTORIO | B17: CUMPLE CON AL MENOS 1 ELEMENTO | C17: NO CUMPLE CON TODOS LOS ELEMENTOS | D17: 0.35
A18: DEFICIENTE | B18: NO CUMPLE CON NINGÚN ELEMENTO | C18: INDISTINTO | D18: 0

Sheet PESOS
A1: CRITERIO | B1: N° | C1: Cod | D1: Indicadores | E1: Tipo | F1: Estándar - Descripción | G1: Estándar - Condicional | H1: Valor Estándar | I1: Pesos | J1: RESULTADO DE AUTOEVALUACION | K1: Escalado | L1: Equivalencia
A2: Organización | B2: 1 | C2: 1.1.1 PEO | D2: Planificación estratégica y operativa | E2: Cualitativo | I2: {=+_xlfn.IFS($U$2=1,BK3,$U$2=2,BL3,$U$2=3,+BM3)} -> 0.04 | J2: 1 | K2: {=+IF(E2="Cuantitativo",_xlfn.IFS(J2<$U$30,0,J2<$U$29,0.35,J2<$U$28,0.7,J2>=$U$28,1),J2)} -> 1 | L2: =+I2*K2 -> 0.04 | T2: MOOD DOCENTES | U2: 1 | V2: =+VLOOKUP(U2,AV10:AW12,2,0) -> A. Pesos Con TP y MT | X2: 2151.1 | BA2: CRITERIO | BB2: SUBCRITERIO | BC2: N° | BD2: Cod | BE2: Ubicación en hoja | BF2: Indicadores | BG2: Tipo | BH2: Estándar - Descripción | BI2: Estándar - Condicional | BJ2: Valor Estándar | BK2: A .Pesos de los indicadores | BL2: B. Pesos sin TP | BM2: C. Pesos sin MT ni TP
A3: Organización | B3: 2 | C3: 1.1.2 RID | D3: Relaciones interinstitucionales para el desarrollo | E3: Cualitativo | I3: {=+_xlfn.IFS($U$2=1,BK4,$U$2=2,BL4,$U$2=3,+BM4)} -> 0.02 | J3: 0.7 | K3: {=+IF(E3="Cuantitativo",_xlfn.IFS(J3<$U$30,0,J3<$U$29,0.35,J3<$U$28,0.7,J3>=$U$28,1),J3)} -> 0.7 | L3: =+I3*K3 -> 0.014 | U3: Objetivo | V3: Evaluación Externa Preparatoria | W3: Conclusión | X3: Evaluación Externa preparatoria | Y3: VALORACIÓN | BA3: Organización | BB3: Planificación y Desarrollo | BC3: 1 | BD3: 1.1.1 PEO | BE3: IND1 1 1PEO | BF3: Planificación estratégica y operativa | BG3: Cualitativo | BK3: 0.04 | BL3: 0.04 | BM3: 0.04
A4: Organización | B4: 3 | C4: 1.1.3 AIC | D4: Aseguramiento interno de la calidad | E4: Cualitativo | I4: {=+_xlfn.IFS($U$2=1,BK5,$U$2=2,BL5,$U$2=3,+BM5)} -> 0.03 | J4: 1 | K4: {=+IF(E4="Cuantitativo",_xlfn.IFS(J4<$U$30,0,J4<$U$29,0.35,J4<$U$28,0.7,J4>=$U$28,1),J4)} -> 1 | L4: =+I4*K4 -> 0.03 | T4: Organización | U4: 1 | V4: =+X4/W4*U4 -> 0.92857143 | W4: =+SUMIF($A$2:B$44,$T4,$I$2:$I$44) -> 0.21 | X4: =+SUMIF($A$2:A$44,$T4,L2:L44) -> 0.195 | Y4: {=+_xlfn.IFS(X4<AE30,T31,X4<AE29,T30,X4<AE28,T29,X4=AE27,T28)} -> Cuasi-satisfactorio | BA4: Organización | BB4: Planificación y Desarrollo | BC4: 2 | BD4: 1.1.2 RID | BE4: IND1 1 2RID | BF4: Relaciones interinstitucionales para el desarrollo | BG4: Cualitativo | BK4: 0.02 | BL4: 0.02 | BM4: 0.02
A5: Organización | B5: 4 | C5: 1.1.4 SIG | D5: Sistema informático de gestión | E5: Cualitativo | I5: {=+_xlfn.IFS($U$2=1,BK6,$U$2=2,BL6,$U$2=3,+BM6)} -> 0.03 | J5: 1 | K5: {=+IF(E5="Cuantitativo",_xlfn.IFS(J5<$U$30,0,J5<$U$29,0.35,J5<$U$28,0.7,J5>=$U$28,1),J5)} -> 1 | L5: =+I5*K5 -> 0.03 | T5: Infraestructura | U5: 1 | V5: =+X5/W5*U5 -> 0.85 | W5: =+SUMIF($A$2:B$44,$T5,$I$2:$I$44) -> 0.1 | X5: =+SUMIF(A3:A45,T5,L3:L45) -> 0.085 | Y5: {=+_xlfn.IFS(X5<AF$30,T$31,X5<AF$29,T$30,X5<AF$28,T$29,X5=AF$27,T$28)} -> Cuasi-satisfactorio | BA5: Organización | BB5: Planificación y Desarrollo | BC5: 3 | BD5: 1.1.3 AIC | BE5: IND1 1 3AIC | BF5: Aseguramiento interno de la calidad | BG5: Cualitativo | BK5: 0.03 | BL5: 0.03 | BM5: 0.03
A6: Organización | B6: 5 | C6: 1.2.1 IDO | D6: Igualdad de oportunidades | E6: Cualitativo | I6: {=+_xlfn.IFS($U$2=1,BK7,$U$2=2,BL7,$U$2=3,+BM7)} -> 0.03 | J6: 0.7 | K6: {=+IF(E6="Cuantitativo",_xlfn.IFS(J6<$U$30,0,J6<$U$29,0.35,J6<$U$28,0.7,J6>=$U$28,1),J6)} -> 0.7 | L6: =+I6*K6 -> 0.021 | T6: Profesores | U6: 1 | V6: =+X6/W6*U6 -> 0.66590909 | W6: =+SUMIF($A$2:B$44,$T6,$I$2:$I$44) -> 0.22 | X6: =+SUMIF(A4:A46,T6,L4:L46) -> 0.1465 | Y6: {=+_xlfn.IFS(X6<AG$30,T$31,X6<AG$29,T$30,X6<AG$28,T$29,X6=AG$27,T$28)} -> Poco Satisfactorio | BA6: Organización | BB6: Planificación y Desarrollo | BC6: 4 | BD6: 1.1.4 SIG | BE6: IND1 1 4SIG | BF6: Sistema informático de gestión | BG6: Cualitativo | BK6: 0.03 | BL6: 0.03 | BM6: 0.03
A7: Organización | B7: 6 | C7: 1.2.2 YET | D7: Ética y transparencia | E7: Cualitativo | I7: {=+_xlfn.IFS($U$2=1,BK8,$U$2=2,BL8,$U$2=3,+BM8)} -> 0.03 | J7: 1 | K7: {=+IF(E7="Cuantitativo",_xlfn.IFS(J7<$U$30,0,J7<$U$29,0.35,J7<$U$28,0.7,J7>=$U$28,1),J7)} -> 1 | L7: =+I7*K7 -> 0.03 | T7: Docencia | U7: 1 | V7: =+X7/W7*U7 -> 0.806 | W7: =+SUMIF($A$2:B$44,$T7,$I$2:$I$44) -> 0.25 | X7: =+SUMIF(A5:A47,T7,L5:L47) -> 0.2015 | Y7: {=+_xlfn.IFS(X7<AH$30,T$31,X7<AH$29,T$30,X7<AH$28,T$29,X7=AH$27,T$28)} -> Cuasi-satisfactorio | BA7: Organización | BB7: Gestión Social | BC7: 5 | BD7: 1.2.1 IDO | BE7: IND1 2 1IDO | BF7: Igualdad de oportunidades | BG7: Cualitativo | BK7: 0.03 | BL7: 0.03 | BM7: 0.03
A8: Organización | B8: 7 | C8: 1.2.3 BPS | D8: Bienestar psicológico | E8: Cualitativo | I8: {=+_xlfn.IFS($U$2=1,BK9,$U$2=2,BL9,$U$2=3,+BM9)} -> 0.03 | J8: 1 | K8: {=+IF(E8="Cuantitativo",_xlfn.IFS(J8<$U$30,0,J8<$U$29,0.35,J8<$U$28,0.7,J8>=$U$28,1),J8)} -> 1 | L8: =+I8*K8 -> 0.03 | T8: I+D e Innovación | U8: 1 | V8: =+X8/W8*U8 -> 0.59375 | W8: =+SUMIF($A$2:B$44,$T8,$I$2:$I$44) -> 0.12 | X8: =+SUMIF(A6:A48,T8,L6:L48) -> 0.07125 | Y8: {=+_xlfn.IFS(X8<AI$30,T$31,X8<AI$29,T$30,X8<AI$28,T$29,X8=AI$27,T$28)} -> Poco Satisfactorio | BA8: Organización | BB8: Gestión Social | BC8: 6 | BD8: 1.2.2 YET | BE8: IND1 2 2EYT | BF8: Ética y transparencia | BG8: Cualitativo | BK8: 0.03 | BL8: 0.03 | BM8: 0.03
A9: Infraestructura | B9: 8 | C9: 2.1.1 PTP | D9: Puestos de trabajo de los profesores | E9: Cuantitativo | F9: Es al menos 1 | G9: >=1 | H9: 1 | I9: {=+_xlfn.IFS($U$2=1,BK10,$U$2=2,BL10,$U$2=3,+BM10)} -> 0.03 | J9: 0.73 | K9: {=+IF(E9="Cuantitativo",_xlfn.IFS(J9<$U$30,0,J9<$U$29,0.35,J9<$U$28,0.7,J9>=$U$28,1),J9)} -> 0.7 | L9: =+I9*K9 -> 0.021 | T9: Vinculación con la sociedad | U9: 1 | V9: =+X9/W9*U9 -> 0.88 | W9: =+SUMIF($A$2:B$44,$T9,$I$2:$I$44) -> 0.1 | X9: =+SUMIF(A7:A49,T9,L7:L49) -> 0.088 | Y9: {=+_xlfn.IFS(X9<AJ$30,T$31,X9<AJ$29,T$30,X9<AJ$28,T$29,X9=AJ$27,T$28)} -> Cuasi-satisfactorio | AV9: ORDEN PESOS | AW9: TIPO PESOS | AX9: Columna | BA9: Organización | BB9: Gestión Social | BC9: 7 | BD9: 1.2.3 BPS | BE9: IND1 2 3BPS | BF9: Bienestar psicológico | BG9: Cualitativo | BK9: 0.03 | BL9: 0.03 | BM9: 0.03
A10: Infraestructura | B10: 9 | C10: 2.1.2 SSO | D10: Seguridad y salud ocupacional | E10: Cualitativo | I10: {=+_xlfn.IFS($U$2=1,BK11,$U$2=2,BL11,$U$2=3,+BM11)} -> 0.025 | J10: 1 | K10: {=+IF(E10="Cuantitativo",_xlfn.IFS(J10<$U$30,0,J10<$U$29,0.35,J10<$U$28,0.7,J10>=$U$28,1),J10)} -> 1 | L10: =+I10*K10 -> 0.025 | W10: =SUM(W4:W9) -> 1 | X10: =SUM(X4:X9) -> 0.78725 | Y10: {=+_xlfn.IFS(X10<AK$30,T$31,X10<AK$29,T$30,X10<AK$28,T$29,X10=AK$27,T$28)} -> Cuasi-satisfactorio | AV10: 1 | AW10: A. Pesos Con TP y MT | AX10: 8 | BA10: Infraestructura | BB10: Infraestructura Básica | BC10: 8 | BD10: 2.1.1 PTP | BE10: IND2 1 1PTP | BF10: Puestos de trabajo de los profesores | BG10: Cuantitativo | BH10: Es al menos 1 | BI10: >=1 | BJ10: 1 | BK10: 0.03 | BL10: 0.03 | BM10: 0.03
A11: Infraestructura | B11: 10 | C11: 2.1.3 AFE | D11: Accesibilidad física y esparcimiento | E11: Cualitativo | I11: {=+_xlfn.IFS($U$2=1,BK12,$U$2=2,BL12,$U$2=3,+BM12)} -> 0.02 | J11: 0.7 | K11: {=+IF(E11="Cuantitativo",_xlfn.IFS(J11<$U$30,0,J11<$U$29,0.35,J11<$U$28,0.7,J11>=$U$28,1),J11)} -> 0.7 | L11: =+I11*K11 -> 0.014 | AV11: 2 | AW11: B. Pesos sin TP | AX11: 9 | BA11: Infraestructura | BB11: Infraestructura Básica | BC11: 9 | BD11: 2.1.2 SSO | BE11: IND2 1 2SSO | BF11: Seguridad y salud ocupacional | BG11: Cualitativo | BK11: 0.025 | BL11: 0.025 | BM11: 0.025
A12: Infraestructura | B12: 11 | C12: 2.1.4 ADB | D12: Ancho de banda | E12: Cuantitativo | F12: al menos 500kb/s | G12: >=500kb/s | H12: 500 | I12: {=+_xlfn.IFS($U$2=1,BK13,$U$2=2,BL13,$U$2=3,+BM13)} -> 0.025 | J12: 3643.15 | K12: {=+IF(E12="Cuantitativo",_xlfn.IFS(J12<$V$30,0,J12<$V$29,0.35,J12<$V$28,0.7,J12>=$V$28,1),J12)} -> 1 | L12: =+I12*K12 -> 0.025 | AV12: 3 | AW12: C. Pesos sin MT ni TP | AX12: 10 | BA12: Infraestructura | BB12: Infraestructura Básica | BC12: 10 | BD12: 2.1.3 AFE | BE12: IND2 1 3AFE | BF12: Accesibilidad física y esparcimiento | BG12: Cualitativo | BK12: 0.02 | BL12: 0.02 | BM12: 0.02
A13: Profesores | B13: 12 | C13: 3.1.1 SDP | D13: Selección de profesores | E13: Cualitativo | I13: {=+_xlfn.IFS($U$2=1,BK14,$U$2=2,BL14,$U$2=3,+BM14)} -> 0.02 | J13: 1 | K13: {=+IF(E13="Cuantitativo",_xlfn.IFS(J13<$U$30,0,J13<$U$29,0.35,J13<$U$28,0.7,J13>=$U$28,1),J13)} -> 1 | L13: =+I13*K13 -> 0.02 | BA13: Infraestructura | BB13: Infraestructura Básica | BC13: 11 | BD13: 2.1.4 ADB | BE13: IND2 1 4ADB | BF13: Ancho de banda | BG13: Cuantitativo | BH13: al menos 500kb/s | BI13: >=500kb/s | BJ13: 500 | BK13: 0.025 | BL13: 0.025 | BM13: 0.025
A14: Profesores | B14: 13 | C14: 3.1.2 FDP | D14: Formación de posgrado | E14: Cuantitativo | F14: Al menos el 50% Tiene Título Maestría o Doctorado | G14: >=50% | H14: 0.5 | I14: {=+_xlfn.IFS($U$2=1,BK15,$U$2=2,BL15,$U$2=3,+BM15)} -> 0.02 | J14: 0.9146 | K14: {=+IF(E14="Cuantitativo",_xlfn.IFS(J14<$W$30,0,J14<$W$29,0.35,J14<$W$28,0.7,J14>=$W$28,1),J14)} -> 1 | L14: =+I14*K14 -> 0.02 | BA14: Profesores | BB14: Selección y Formación Previa | BC14: 12 | BD14: 3.1.1 SDP | BE14: IND3 1 1SDP | BF14: Selección de profesores | BG14: Cualitativo | BK14: 0.02 | BL14: 0.022 | BM14: 0.023
A15: Profesores | B15: 14 | C15: 3.1.3 ETC | D15: Experiencia profesional práctica de profesores TC de contenidos profesionales | E15: Cuantitativo | F15: Al menos el 50% Tiene Experiencia práctica acumulada de min. 3 años | G15: >=50% | H15: 0.5 | I15: {=+_xlfn.IFS($U$2=1,BK16,$U$2=2,BL16,$U$2=3,+BM16)} -> 0.02 | J15: 0.8763 | K15: {=+IF(E15="Cuantitativo",_xlfn.IFS(J15<$W$30,0,J15<$W$29,0.35,J15<$W$28,0.7,J15>=$W$28,1),J15)} -> 1 | L15: =+I15*K15 -> 0.02 | BA15: Profesores | BB15: Selección y Formación Previa | BC15: 13 | BD15: 3.1.2 FDP | BE15: IND3 1 2FDP | BF15: Formación de posgrado | BG15: Cuantitativo | BH15: Al menos el 50% Tiene Título Maestría o Doctorado | BI15: >=50% | BJ15: 0.5 | BK15: 0.02 | BL15: 0.022 | BM15: 0.023
A16: Profesores | B16: 15 | C16: 3.1.4 EMP | D16: Ejercicio profesional práctico de profesores MT y TP de contenidos profesionales | E16: Cuantitativo | F16: El 100% (MT y TP) realizaron ejercicio profesional afin a contenido por 24meses o más | G16: "=100%" | H16: 1 | I16: {=+_xlfn.IFS($U$2=1,BK17,$U$2=2,BL17,$U$2=3,+BM17)} -> 0.03 | J16: 0.6612 | K16: {=+IF(E16="Cuantitativo",_xlfn.IFS(J16<$U$30,0,J16<$U$29,0.35,J16<$U$28,0.7,J16>=$U$28,1),J16)} -> 0.35 | L16: =+I16*K16 -> 0.0105 | BA16: Profesores | BB16: Selección y Formación Previa | BC16: 14 | BD16: 3.1.3 ETC | BE16: IND3 1 3ETC | BF16: Experiencia profesional práctica de profesores TC de contenidos profesionales | BG16: Cuantitativo | BH16: Al menos el 50% Tiene Experiencia práctica acumulada de min. 3 años | BI16: >=50% | BJ16: 0.5 | BK16: 0.02 | BL16: 0.022 | BM16: 0.026
A17: Profesores | B17: 16 | C17: 3.2.1 TPD | D17: Titularidad de profesores TC y MT | E17: Cuantitativo | F17: Al menos el 30% TC y MT son titulares por concurso | G17: >=30% | H17: 0.3 | I17: {=+_xlfn.IFS($U$2=1,BK18,$U$2=2,BL18,$U$2=3,+BM18)} -> 0.02 | J17: 0 | K17: {=+IF(E17="Cuantitativo",_xlfn.IFS(J17<$X$30,0,J17<$X$29,0.35,J17<$X$28,0.7,J17>=$X$28,1),J17)} -> 0 | L17: =+I17*K17 -> 0 | BA17: Profesores | BB17: Selección y Formación Previa | BC17: 15 | BD17: 3.1.4 EMP | BE17: IND3 1 4EMP | BF17: Ejercicio profesional práctico de profesores MT y TP de contenidos profesionales | BG17: Cuantitativo | BH17: El 100% (MT y TP) realizaron ejercicio profesional afin a contenido por 24meses o más | BI17: "=100%" | BJ17: 1 | BK17: 0.03 | BL17: 0.032
A18: Profesores | B18: 17 | C18: 3.2.2 CHS | D18: Carga horaria semanal de los profesores TC | E18: Cuantitativo | F18: Hasta 18 horas clase semanal | G18: <=18 | H18: 18 | I18: {=+_xlfn.IFS($U$2=1,BK19,$U$2=2,BL19,$U$2=3,+BM19)} -> 0.02 | J18: 7.94 | K18: {=+IF(E18="Cuantitativo",_xlfn.IFS(J18<$Y$30,0,J18<$Y$29,0.35,J18<$Y$28,0.7,J18>=$Y$28,1),J18)} -> 0.35 | L18: =+I18*K18 -> 0.007 | BA18: Profesores | BB18: Organización y Desarrollo | BC18: 16 | BD18: 3.2.1 TPD | BE18: IND3 2 1TDP | BF18: Titularidad de profesores TC y MT | BG18: Cuantitativo | BH18: Al menos el 30% TC y MT son titulares por concurso | BI18: >=30% | BJ18: 0.3 | BK18: 0.02 | BL18: 0.022 | BM18: 0.023
A19: Profesores | B19: 18 | C19: 3.2.3 EDP | D19: Evaluación de profesores | E19: Cualitativo | I19: {=+_xlfn.IFS($U$2=1,BK20,$U$2=2,BL20,$U$2=3,+BM20)} -> 0.02 | J19: 1 | K19: {=+IF(E19="Cuantitativo",_xlfn.IFS(J19<$Y$30,0,J19<$Y$29,0.35,J19<$Y$28,0.7,J19>=$Y$28,1),J19)} -> 1 | L19: =+I19*K19 -> 0.02 | BA19: Profesores | BB19: Organización y Desarrollo | BC19: 17 | BD19: 3.2.2 CHS | BE19: IND3 2 2CHS | BF19: Carga horaria semanal de los profesores TC | BG19: Cuantitativo | BH19: Hasta 18 horas clase semanal | BI19: <=18 | BJ19: 18 | BK19: 0.02 | BL19: 0.022 | BM19: 0.023
A20: Profesores | B20: 19 | C20: 3.2.4 FAC | D20: Formación académica en curso y capacitación | E20: Cualitativo | I20: {=+_xlfn.IFS($U$2=1,BK21,$U$2=2,BL21,$U$2=3,+BM21)} -> 0.03 | J20: 0.7 | K20: {=+IF(E20="Cuantitativo",_xlfn.IFS(J20<$Y$30,0,J20<$Y$29,0.35,J20<$Y$28,0.7,J20>=$Y$28,1),J20)} -> 0.7 | L20: =+I20*K20 -> 0.021 | BA20: Profesores | BB20: Organización y Desarrollo | BC20: 18 | BD20: 3.2.3 EDP | BE20: IND3 2 3EDP | BF20: Evaluación de profesores | BG20: Cualitativo | BK20: 0.02 | BL20: 0.022 | BM20: 0.023
A21: Profesores | B21: 20 | C21: 3.3.1 RPM | D21: Remuneración promedio mensual TC y MT | E21: Cuantitativo | F21: Al menos $ 1100.00 | G21: >=1100.00 | H21: 1100 | I21: {=+_xlfn.IFS($U$2=1,BK22,$U$2=2,BL22,$U$2=3,+BM22)} -> 0.02 | J21: 970.78 | K21: {=+IF(E21="Cuantitativo",_xlfn.IFS(J21<$Z$30,0,J21<$Z$29,0.35,J21<$Z$28,0.7,J21>=$Z$28,1),J21)} -> 0.7 | L21: =+I21*K21 -> 0.014 | BA21: Profesores | BB21: Organización y Desarrollo | BC21: 19 | BD21: 3.2.4 FAC | BE21: IND3 2 4FAC | BF21: Formación académica en curso y capacitación | BG21: Cualitativo | BK21: 0.03 | BL21: 0.032 | BM21: 0.033
A22: Profesores | B22: 21 | C22: 3.3.2 RPH | D22: Remuneración promedio por hora TP | E22: Cuantitativo | F22: Al menos $ 13.00 | G22: >=13.00 | H22: 13 | I22: {=+_xlfn.IFS($U$2=1,BK23,$U$2=2,BL23,$U$2=3,+BM23)} -> 0.02 | J22: 10.73 | K22: {=+IF(E22="Cuantitativo",_xlfn.IFS(J22<$AA$30,0,J22<$AA$29,0.35,J22<$AA$28,0.7,J22>=$AA$28,1),J22)} -> 0.7 | L22: =+I22*K22 -> 0.014 | BA22: Profesores | BB22: Remuneraciones | BC22: 20 | BD22: 3.3.1 RPM | BE22: IND3 3 1RPM | BF22: Remuneración promedio mensual TC y MT | BG22: Cuantitativo | BH22: Al menos $ 1100.00 | BI22: >=1100.00 | BJ22: 1100 | BK22: 0.02 | BL22: 0.024 | BM22: 0.023
A23: Docencia | B23: 22 | C23: 4.1.1 PEA | D23: Programas de estudio de las asignaturas | E23: Cuantitativo | F23: El 100% de los PEA cumplen los requisitos | G23: "=100%" | H23: 1 | I23: {=+_xlfn.IFS($U$2=1,BK24,$U$2=2,BL24,$U$2=3,+BM24)} -> 0.015 | J23: 1 | K23: {=+IF(E23="Cuantitativo",_xlfn.IFS(J23<$U$30,0,J23<$U$29,0.35,J23<$U$28,0.7,J23>=$U$28,1),J23)} -> 1 | L23: =+I23*K23 -> 0.015 | BA23: Profesores | BB23: Remuneraciones | BC23: 21 | BD23: 3.3.2 RPH | BE23: IND3 3 2RPH | BF23: Remuneración promedio por hora TP | BG23: Cuantitativo | BH23: Al menos $ 13.00 | BI23: >=13.00 | BJ23: 13 | BK23: 0.02 | BM23: 0.023
A24: Docencia | B24: 23 | C24: 4.1.2 AFD | D24: Afinidad formación-docencia | E24: Cuantitativo | F24: El 100% de horas clase impartidas por profesores con título 3er nivel o mayor afín a la asignatura | G24: "=100%" | H24: 1 | I24: {=+_xlfn.IFS($U$2=1,BK25,$U$2=2,BL25,$U$2=3,+BM25)} -> 0.015 | J24: 1 | K24: {=+IF(E24="Cuantitativo",_xlfn.IFS(J24<$U$30,0,J24<$U$29,0.35,J24<$U$28,0.7,J24>=$U$28,1),J24)} -> 1 | L24: =+I24*K24 -> 0.015 | BA24: Docencia | BB24: Formación Académica | BC24: 22 | BD24: 4.1.1 PEA | BE24: IND4 1 1PEA | BF24: Programas de estudio de las asignaturas | BG24: Cuantitativo | BH24: El 100% de los PEA cumplen los requisitos | BI24: "=100%" | BJ24: 1 | BK24: 0.015 | BL24: 0.015 | BM24: 0.015
A25: Docencia | B25: 24 | C25: 4.1.3 SPD | D25: Seguimiento, control y evaluación del proceso docente | E25: Cualitativo | I25: {=+_xlfn.IFS($U$2=1,BK26,$U$2=2,BL26,$U$2=3,+BM26)} -> 0.015 | J25: 0.35 | K25: {=+IF(E25="Cuantitativo",_xlfn.IFS(J25<$U$30,0,J25<$U$29,0.35,J25<$U$28,0.7,J25>=$U$28,1),J25)} -> 0.35 | L25: =+I25*K25 -> 0.00525 | BA25: Docencia | BB25: Formación Académica | BC25: 23 | BD25: 4.1.2 AFD | BE25: IND4 1 2AFD | BF25: Afinidad formación-docencia | BG25: Cuantitativo | BH25: El 100% de horas clase impartidas por profesores con título 3er nivel o mayor afín a la asignatura | BI25: "=100%" | BJ25: 1 | BK25: 0.015 | BL25: 0.015 | BM25: 0.015
A26: Docencia | B26: 25 | C26: 4.1.4 CBA | D26: Asignaturas con cobertura bibliográfica adecuada | E26: Cuantitativo | F26: El 100% de Asignaturas cobertura bibliográfica | G26: "=100%" | H26: 1 | I26: {=+_xlfn.IFS($U$2=1,BK27,$U$2=2,BL27,$U$2=3,+BM27)} -> 0.01 | J26: 1 | K26: {=+IF(E26="Cuantitativo",_xlfn.IFS(J26<$U$30,0,J26<$U$29,0.35,J26<$U$28,0.7,J26>=$U$28,1),J26)} -> 1 | L26: =+I26*K26 -> 0.01 | BA26: Docencia | BB26: Formación Académica | BC26: 24 | BD26: 4.1.3 SPD | BE26: IND4 1 3SPD | BF26: Seguimiento, control y evaluación del proceso docente | BG26: Cualitativo | BK26: 0.015 | BL26: 0.015 | BM26: 0.015
A27: Docencia | B27: 26 | C27: 4.1.5 PUB | D27: Publicaciones docentes | E27: Cuantitativo | F27: Al menos 0.6 | G27: >=0.6 | H27: 0.6 | I27: {=+_xlfn.IFS($U$2=1,BK28,$U$2=2,BL28,$U$2=3,+BM28)} -> 0.015 | J27: 3 | K27: {=+IF(E27="Cuantitativo",_xlfn.IFS(J27<$AB$30,0,J27<$AB$29,0.35,J27<$AB$28,0.7,J27>=$AB$28,1),J27)} -> 1 | L27: =+I27*K27 -> 0.015 | V27: 500 | W27: 0.5 | X27: 0.3 | Y27: 18 | Z27: 1100 | AA27: 13 | AB27: 0.6 | AC27: 0.5 | AE27: =+SUMIF($A$2:B$44,$T4,$I$2:$I$44) -> 0.21 | AF27: =+SUMIF($A$2:B$44,$T5,$I$2:$I$44) -> 0.1 | AG27: =+SUMIF($A$2:B$44,$T6,$I$2:$I$44) -> 0.22 | AH27: =+SUMIF($A$2:B$44,$T7,$I$2:$I$44) -> 0.25 | AI27: =+SUMIF($A$2:B$44,$T8,$I$2:$I$44) -> 0.12 | AJ27: =+SUMIF($A$2:B$44,$T9,$I$2:$I$44) -> 0.1 | AK27: 1 | BA27: Docencia | BB27: Formación Académica | BC27: 25 | BD27: 4.1.4 CBA | BE27: IND4 1 4CBA | BF27: Asignaturas con cobertura bibliográfica adecuada | BG27: Cuantitativo | BH27: El 100% de Asignaturas cobertura bibliográfica | BI27: "=100%" | BJ27: 1 | BK27: 0.01 | BL27: 0.01 | BM27: 0.01
A28: Docencia | B28: 27 | C28: 4.1.6 AUL | D28: Aulas | E28: Cuantitativo | F28: El 100% de las aulas cumple los requisitos | G28: "=100%" | H28: 1 | I28: {=+_xlfn.IFS($U$2=1,BK29,$U$2=2,BL29,$U$2=3,+BM29)} -> 0.01 | J28: 1 | K28: {=+IF(E28="Cuantitativo",_xlfn.IFS(J28<$U$30,0,J28<$U$29,0.35,J28<$U$28,0.7,J28>=$U$28,1),J28)} -> 1 | L28: =+I28*K28 -> 0.01 | T28: Satisfactorio | U28: 1 | V28: =+U28*$V$27 -> 500 | W28: =+U28*$W$27 -> 0.5 | X28: =+U28*$X$27 -> 0.3 | Y28: =+$U28*Y$27 -> 18 | Z28: =+$U28*Z$27 -> 1100 | AA28: =+$U28*AA$27 -> 13 | AB28: =+$U28*AB$27 -> 0.6 | AC28: =+$U28*AC$27 -> 0.5 | AE28: =+$U28*AE$27 -> 0.21 | AF28: =+$U28*AF$27 -> 0.1 | AG28: =+$U28*AG$27 -> 0.22 | AH28: =+$U28*AH$27 -> 0.25 | AI28: =+$U28*AI$27 -> 0.12 | AJ28: =+$U28*AJ$27 -> 0.1 | AK28: =+$U28*AK$27 -> 1 | BA28: Docencia | BB28: Formación Académica | BC28: 26 | BD28: 4.1.5 PUB | BE28: IND4 1 5PUB | BF28: Publicaciones docentes | BG28: Cuantitativo | BH28: Al menos 0.6 | BI28: >=0.6 | BJ28: 0.6 | BK28: 0.015 | BL28: 0.015 | BM28: 0.015
A29: Docencia | B29: 28 | C29: 4.1.7 FCO | D29: Formación complementaria | E29: Cualitativo | I29: {=+_xlfn.IFS($U$2=1,BK30,$U$2=2,BL30,$U$2=3,+BM30)} -> 0.015 | J29: 0.7 | K29: {=+IF(E29="Cuantitativo",_xlfn.IFS(J29<$U$30,0,J29<$U$29,0.35,J29<$U$28,0.7,J29>=$U$28,1),J29)} -> 0.7 | L29: =+I29*K29 -> 0.0105 | T29: Cuasi-satisfactorio | U29: 0.7 | V29: =+U29*$V$27 -> 350 | W29: =+U29*$W$27 -> 0.35 | X29: =+U29*$X$27 -> 0.21 | Y29: =+$U29*$Y$27 -> 12.6 | Z29: =+$U29*Z$27 -> 770 | AA29: =+$U29*AA$27 -> 9.1 | AB29: =+$U29*AB$27 -> 0.42 | AC29: =+$U29*AC$27 -> 0.35 | AE29: =+$U29*AE$27 -> 0.147 | AF29: =+$U29*AF$27 -> 0.07 | AG29: =+$U29*AG$27 -> 0.154 | AH29: =+$U29*AH$27 -> 0.175 | AI29: =+$U29*AI$27 -> 0.084 | AJ29: =+$U29*AJ$27 -> 0.07 | AK29: =+$U29*AK$27 -> 0.7 | BA29: Docencia | BB29: Formación Académica | BC29: 27 | BD29: 4.1.6 AUL | BE29: IND4 1 6AUL | BF29: Aulas | BG29: Cuantitativo | BH29: El 100% de las aulas cumple los requisitos | BI29: "=100%" | BJ29: 1 | BK29: 0.01 | BL29: 0.01 | BM29: 0.01
A30: Docencia | B30: 29 | C30: 4.1.8 APE | D30: Acompañamiento pedagógico a estudiantes | E30: Cualitativo | I30: {=+_xlfn.IFS($U$2=1,BK31,$U$2=2,BL31,$U$2=3,+BM31)} -> 0.02 | J30: 0.7 | K30: {=+IF(E30="Cuantitativo",_xlfn.IFS(J30<$U$30,0,J30<$U$29,0.35,J30<$U$28,0.7,J30>=$U$28,1),J30)} -> 0.7 | L30: =+I30*K30 -> 0.014 | T30: Poco Satisfactorio | U30: 0.35 | V30: =+U30*$V$27 -> 175 | W30: =+U30*$W$27 -> 0.175 | X30: =+U30*$X$27 -> 0.105 | Y30: =+$U30*$Y$27 -> 6.3 | Z30: =+$U30*Z$27 -> 385 | AA30: =+$U30*AA$27 -> 4.55 | AB30: =+$U30*AB$27 -> 0.21 | AC30: =+$U30*AC$27 -> 0.175 | AE30: =+$U30*AE$27 -> 0.0735 | AF30: =+$U30*AF$27 -> 0.035 | AG30: =+$U30*AG$27 -> 0.077 | AH30: =+$U30*AH$27 -> 0.0875 | AI30: =+$U30*AI$27 -> 0.042 | AJ30: =+$U30*AJ$27 -> 0.035 | AK30: =+$U30*AK$27 -> 0.35 | BA30: Docencia | BB30: Formación Académica | BC30: 28 | BD30: 4.1.7 FCO | BE30: IND4 1 7FCO | BF30: Formación complementaria | BG30: Cualitativo | BK30: 0.015 | BL30: 0.015 | BM30: 0.015
A31: Docencia | B31: 30 | C31: 4.1.9 RCG | D31: Relación con los graduados | E31: Cualitativo | I31: {=+_xlfn.IFS($U$2=1,BK32,$U$2=2,BL32,$U$2=3,+BM32)} -> 0.01 | J31: 0.35 | K31: {=+IF(E31="Cuantitativo",_xlfn.IFS(J31<$U$30,0,J31<$U$29,0.35,J31<$U$28,0.7,J31>=$U$28,1),J31)} -> 0.35 | L31: =+I31*K31 -> 0.0035 | T31: Deficiente | U31: 0 | V31: =+U31*$V$27 -> 0 | W31: =+U31*$W$27 -> 0 | X31: =+U31*$X$27 -> 0 | Y31: =+$U31*$Y$27 -> 0 | Z31: =+$U31*Z$27 -> 0 | AA31: =+$U31*AA$27 -> 0 | AB31: =+$U31*AB$27 -> 0 | AC31: =+$U31*AC$27 -> 0 | BA31: Docencia | BB31: Formación Académica | BC31: 29 | BD31: 4.1.8 APE | BE31: IND4 1 8APE | BF31: Acompañamiento pedagógico a estudiantes | BG31: Cualitativo | BK31: 0.02 | BL31: 0.02 | BM31: 0.02
A32: Docencia | B32: 31 | C32: 4.2.1 EVA | D32: Entorno virtual de aprendizaje | E32: Cualitativo | I32: {=+_xlfn.IFS($U$2=1,BK33,$U$2=2,BL33,$U$2=3,+BM33)} -> 0.015 | J32: 1 | K32: {=+IF(E32="Cuantitativo",_xlfn.IFS(J32<$U$30,0,J32<$U$29,0.35,J32<$U$28,0.7,J32>=$U$28,1),J32)} -> 1 | L32: =+I32*K32 -> 0.015 | BA32: Docencia | BB32: Formación Académica | BC32: 30 | BD32: 4.1.9 RCG | BE32: IND4 1 9RCG | BF32: Relación con los graduados | BG32: Cualitativo | BK32: 0.01 | BL32: 0.01 | BM32: 0.01
A33: Docencia | B33: 32 | C33: 4.2.2 IEA | D33: Informatización en el aprendizaje | E33: Cualitativo | I33: {=+_xlfn.IFS($U$2=1,BK34,$U$2=2,BL34,$U$2=3,+BM34)} -> 0.015 | J33: 0.7 | K33: {=+IF(E33="Cuantitativo",_xlfn.IFS(J33<$U$30,0,J33<$U$29,0.35,J33<$U$28,0.7,J33>=$U$28,1),J33)} -> 0.7 | L33: =+I33*K33 -> 0.0105 | BA33: Docencia | BB33: Informatización del Proceso de Enseñanza | BC33: 31 | BD33: 4.2.1 EVA | BE33: IND4 2 1EVA | BF33: Entorno virtual de aprendizaje | BG33: Cualitativo | BK33: 0.015 | BL33: 0.015 | BM33: 0.015
A34: Docencia | B34: 33 | C34: 4.3.1 EAD | D34: Educación ambiental y desarrollo sostenible | E34: Cualitativo | I34: {=+_xlfn.IFS($U$2=1,BK35,$U$2=2,BL35,$U$2=3,+BM35)} -> 0.01 | J34: 0.7 | K34: {=+IF(E34="Cuantitativo",_xlfn.IFS(J34<$U$30,0,J34<$U$29,0.35,J34<$U$28,0.7,J34>=$U$28,1),J34)} -> 0.7 | L34: =+I34*K34 -> 0.007 | BA34: Docencia | BB34: Informatización del Proceso de Enseñanza | BC34: 32 | BD34: 4.2.2 IEA | BE34: IND4 2 2IEA | BF34: Informatización en el aprendizaje | BG34: Cualitativo | BK34: 0.015 | BL34: 0.015 | BM34: 0.015
A35: Docencia | B35: 34 | C35: 4.3.2 VHB | D35: Formación en valores y desarrollo de habilidades blandas | E35: Cualitativo | I35: {=+_xlfn.IFS($U$2=1,BK36,$U$2=2,BL36,$U$2=3,+BM36)} -> 0.015 | J35: 0.35 | K35: {=+IF(E35="Cuantitativo",_xlfn.IFS(J35<$U$30,0,J35<$U$29,0.35,J35<$U$28,0.7,J35>=$U$28,1),J35)} -> 0.35 | L35: =+I35*K35 -> 0.00525 | BA35: Docencia | BB35: Formación Ciudadana | BC35: 33 | BD35: 4.3.1 EAD | BE35: IND4 3 1EAD | BF35: Educación ambiental y desarrollo sostenible | BG35: Cualitativo | BK35: 0.01 | BL35: 0.01 | BM35: 0.01
A36: Docencia | B36: 35 | C36: 4.4.1 FPA | D36: Formación práctica en el entorno académico | E36: Cualitativo | I36: {=+_xlfn.IFS($U$2=1,BK37,$U$2=2,BL37,$U$2=3,+BM37)} -> 0.02 | J36: 1 | K36: {=+IF(E36="Cuantitativo",_xlfn.IFS(J36<$U$30,0,J36<$U$29,0.35,J36<$U$28,0.7,J36>=$U$28,1),J36)} -> 1 | L36: =+I36*K36 -> 0.02 | BA36: Docencia | BB36: Formación Ciudadana | BC36: 34 | BD36: 4.3.2 VHB | BE36: IND4 3 2VHB | BF36: Formación en valores y desarrollo de habilidades blandas | BG36: Cualitativo | BK36: 0.015 | BL36: 0.015 | BM36: 0.015
A37: Docencia | B37: 36 | C37: 4.4.2 FPL | D37: Formación práctica en el entorno laboral real | E37: Cualitativo | I37: {=+_xlfn.IFS($U$2=1,BK38,$U$2=2,BL38,$U$2=3,+BM38)} -> 0.02 | J37: 1 | K37: {=+IF(E37="Cuantitativo",_xlfn.IFS(J37<$U$30,0,J37<$U$29,0.35,J37<$U$28,0.7,J37>=$U$28,1),J37)} -> 1 | L37: =+I37*K37 -> 0.02 | BA37: Docencia | BB37: Formación Práctica | BC37: 35 | BD37: 4.4.1 FPA | BE37: IND4 4 1FPA | BF37: Formación práctica en el entorno académico | BG37: Cualitativo | BK37: 0.02 | BL37: 0.02 | BM37: 0.02
A38: Docencia | B38: 37 | C38: 4.5.1 BIB | D38: Funcionamiento de la biblioteca | E38: Cualitativo | I38: {=+_xlfn.IFS($U$2=1,BK39,$U$2=2,BL39,$U$2=3,+BM39)} -> 0.015 | J38: 1 | K38: {=+IF(E38="Cuantitativo",_xlfn.IFS(J38<$U$30,0,J38<$U$29,0.35,J38<$U$28,0.7,J38>=$U$28,1),J38)} -> 1 | L38: =+I38*K38 -> 0.015 | BA38: Docencia | BB38: Formación Práctica | BC38: 36 | BD38: 4.4.2 FPL | BE38: IND4 4 2FPL | BF38: Formación práctica en el entorno laboral real | BG38: Cualitativo | BK38: 0.02 | BL38: 0.02 | BM38: 0.02
A39: Docencia | B39: 38 | C39: 4.5.2 BAC | D39: Acervo de la biblioteca y relación de la biblioteca con las asignaturas y carreras | E39: Cualitativo | I39: {=+_xlfn.IFS($U$2=1,BK40,$U$2=2,BL40,$U$2=3,+BM40)} -> 0.015 | J39: 0.7 | K39: {=+IF(E39="Cuantitativo",_xlfn.IFS(J39<$U$30,0,J39<$U$29,0.35,J39<$U$28,0.7,J39>=$U$28,1),J39)} -> 0.7 | L39: =+I39*K39 -> 0.0105 | BA39: Docencia | BB39: Biblioteca | BC39: 37 | BD39: 4.5.1 BIB | BE39: IND4 5 1BIB | BF39: Funcionamiento de la biblioteca | BG39: Cualitativo | BK39: 0.015 | BL39: 0.015 | BM39: 0.015
A40: I+D e Innovación | B40: 39 | C40: 5.1.1 IYD | D40: Investigación y desarrollo | E40: Cualitativo | I40: {=+_xlfn.IFS($U$2=1,BK41,$U$2=2,BL41,$U$2=3,+BM41)} -> 0.045 | J40: 0.35 | K40: {=+IF(E40="Cuantitativo",_xlfn.IFS(J40<$U$30,0,J40<$U$29,0.35,J40<$U$28,0.7,J40>=$U$28,1),J40)} -> 0.35 | L40: =+I40*K40 -> 0.01575 | BA40: Docencia | BB40: Biblioteca | BC40: 38 | BD40: 4.5.2 BAC | BE40: IND4 5 2BAC | BF40: Acervo de la biblioteca y relación de la biblioteca con las asignaturas y carreras | BG40: Cualitativo | BK40: 0.015 | BL40: 0.015 | BM40: 0.015
A41: I+D e Innovación | B41: 40 | C41: 5.1.2PCT | D41: Publicaciones y eventos científicos y técnicos | E41: Cuantitativo | F41: Al menos 0.5 | G41: >=0.5 | H41: 0.5 | I41: {=+_xlfn.IFS($U$2=1,BK42,$U$2=2,BL42,$U$2=3,+BM42)} -> 0.045 | J41: 1 | K41: {=+IF(E41="Cuantitativo",_xlfn.IFS(J41<$AC$30,0,J41<$AC$29,0.35,J41<$AC$28,0.7,J41>=$AC$28,1),J41)} -> 1 | L41: =+I41*K41 -> 0.045 | BA41: I+D e Innovación | BB41: I+D y Publicaciones Científicas y Técnicas | BC41: 39 | BD41: 5.1.1 IYD | BE41: IND5 1 1IYD | BF41: Investigación y desarrollo | BG41: Cualitativo | BK41: 0.045 | BL41: 0.045 | BM41: 0.045
A42: I+D e Innovación | B42: 41 | C42: 5.2.1 ICA | D42: Innovación y capacidad de absorción | E42: Cualitativo | I42: {=+_xlfn.IFS($U$2=1,BK43,$U$2=2,BL43,$U$2=3,+BM43)} -> 0.03 | J42: 0.35 | K42: {=+IF(E42="Cuantitativo",_xlfn.IFS(J42<$U$30,0,J42<$U$29,0.35,J42<$U$28,0.7,J42>=$U$28,1),J42)} -> 0.35 | L42: =+I42*K42 -> 0.0105 | BA42: I+D e Innovación | BB42: I+D y Publicaciones Científicas y Técnicas | BC42: 40 | BD42: 5.1.2PCT | BE42: IND5 1 2PCT | BF42: Publicaciones y eventos científicos y técnicos | BG42: Cuantitativo | BH42: Al menos 0.5 | BI42: >=0.5 | BJ42: 0.5 | BK42: 0.045 | BL42: 0.045 | BM42: 0.045
A43: Vinculación con la sociedad | B43: 42 | C43: 6.1.1 PEV | D43: Planificación y ejecución de la vinculación con la sociedad | E43: Cualitativo | I43: {=+_xlfn.IFS($U$2=1,BK44,$U$2=2,BL44,$U$2=3,+BM44)} -> 0.06 | J43: 1 | K43: {=+IF(E43="Cuantitativo",_xlfn.IFS(J43<$U$30,0,J43<$U$29,0.35,J43<$U$28,0.7,J43>=$U$28,1),J43)} -> 1 | L43: =+I43*K43 -> 0.06 | BA43: I+D e Innovación | BB43: Innovación | BC43: 41 | BD43: 5.2.1 ICA | BE43: IND5 2 1ICA | BF43: Innovación y capacidad de absorción | BG43: Cualitativo | BK43: 0.03 | BL43: 0.03 | BM43: 0.03
A44: Vinculación con la sociedad | B44: 43 | C44: 6.2.1 PIC | D44: Presencia de la institución en la comunidad | E44: Cualitativo | I44: {=+_xlfn.IFS($U$2=1,BK45,$U$2=2,BL45,$U$2=3,+BM45)} -> 0.04 | J44: 0.7 | K44: {=+IF(E44="Cuantitativo",_xlfn.IFS(J44<$U$30,0,J44<$U$29,0.35,J44<$U$28,0.7,J44>=$U$28,1),J44)} -> 0.7 | L44: =+I44*K44 -> 0.028 | BA44: Vinculación con la sociedad | BB44: Planificación y Ejecución de la Vinculación | BC44: 42 | BD44: 6.1.1 PEV | BE44: IND6 1 1PEV | BF44: Planificación y ejecución de la vinculación con la sociedad | BG44: Cualitativo | BK44: 0.06 | BL44: 0.06 | BM44: 0.06
I45: =SUM(I2:I44) -> 1 | L45: =SUM(L2:L44) -> 0.78725 | BA45: Vinculación con la sociedad | BB45: Presencia en la Comunidad | BC45: 43 | BD45: 6.2.1 PIC | BE45: IND6 2 1PIC | BF45: Presencia de la institución en la comunidad | BG45: Cualitativo | BK45: 0.04 | BL45: 0.04 | BM45: 0.04
